Workbook

Sheet Team Summary
A1: My Team — NPS Detractor Insights
A2: VXI · Comcast · 12 agents · 26 unique surveys (25-Sep → 06-Oct-2026) · scrubbed by Omar Mansour
A5: Surveys | C5: Agent Opp % | E5: Comcast % | G5: Customer % | I5: No Audio % | K5: Agents to Coach
A6: =COUNTA('Team Data'!$D$2:$D$27) -> 26 | C6: =COUNTIFS('Team Data'!$G$2:$G$27,"Agent Opportunity")/COUNTA('Team Data'!$D$2:$D$27) -> 0.42307692 | E6: =COUNTIFS('Team Data'!$G$2:$G$27,"Comcast Process/Tools")/COUNTA('Team Data'!$D$2:$D$27) -> 0.34615385 | G6: =COUNTIFS('Team Data'!$G$2:$G$27,"Customer")/COUNTA('Team Data'!$D$2:$D$27) -> 0.15384615 | I6: =COUNTIFS('Team Data'!$G$2:$G$27,"No Audio Found on I3")/COUNTA('Team Data'!$D$2:$D$27) -> 0.076923077 | K6: =COUNTIFS('Agent Scorecard'!J6:J17,"High")+COUNTIFS('Agent Scorecard'!J6:J17,"Medium") -> 6
A8: Key Insights
A9: 1. 11 of 26 surveys (42%) are agent-controllable. The other 58% are Comcast issues (outage, technician, restrictions), customer-side, or no audio, so they are outside the agent's control. The account rate is 64%.
A10: 2. Communication / Soft Skills drives 6 of the 11 Agent Opp detractors (55%): empathy, listening to what the customer is actually asking, and setting expectations.
A11: 3. 3 agents account for 7 of the 11 (64%): bp-akahal350 (3), bp-mammar838 (2), bp-mtadro821 (2). Focus coaching here first.
A12: 4. Day over day: 06-Oct was the busiest survey day (5 detractors, but only 1 Agent Opp). 05-Oct had the highest Agent Opp share (2 of 3). 28-Sep and 01-Oct each had 2 Agent Opp.
A13: 5. Hold/Mute and dropped calls (mtadro821, aelshe876, ahassa042) are repeat-call risks. Link them to aiCR.
A14: 6. 5 agents have NO controllable detractor (okamel106, yabdel208, aali048, jsolim238, mmahmo022), and aelshe876 received 2 positive-feedback comments from customers. Recognise them in the team huddle.
A16: Actions by KPI
A17: ▶ QA: 1:1 side-by-side for akahal350, mammar838 and mtadro821 this week. Use the scrub evidence in the Coaching Log.
A18: ▶ Repeat (aiCR): coach ownership (call back after a disconnect) and resolving the primary reason first. Re-check these BPIDs on aiCR in 14 days.
A19: ▶ Transfer: yawade572 should warm-transfer with empathy and explain the reason, especially for repeat callers.
A20: ▶ Team leaders (newly promoted): split the 6 agents to coach (High + Medium) across your 3 TLs in the Agent Scorecard (yellow column), then log each session in the Coaching Log.
... A23: Rates and counts are live formulas on Team Data. Insight text was written from the data on 07-Oct-2026. Duplicates were removed (latest submission kept) and the test row was excluded.

Sheet Agent Scorecard
A1: My Team — Agent Scorecard
A2: 12 agents · NPS detractor scrubs · unique surveys · sorted by coaching priority
A5: BPID | B5: Agent | C5: Surveys | D5: Agent Opp | E5: Comcast | F5: Customer | G5: No Audio | H5: Agent Opp % | I5: Main Agent Opp Driver | J5: Priority | K5: Coaching Action | L5: KPI Link | M5: Team Leader (fill in) | N5: Coached? (fill in)
A6: bp-akahal350 | B6: Ahmed | C6: =COUNTIFS('Team Data'!$D$2:$D$27,A6) -> 4 | D6: =COUNTIFS('Team Data'!$D$2:$D$27,$A6,'Team Data'!$G$2:$G$27,"Agent Opportunity") -> 3 | E6: =COUNTIFS('Team Data'!$D$2:$D$27,$A6,'Team Data'!$G$2:$G$27,"Comcast Process/Tools") -> 1 | F6: =COUNTIFS('Team Data'!$D$2:$D$27,$A6,'Team Data'!$G$2:$G$27,"Customer") -> 0 | G6: =COUNTIFS('Team Data'!$D$2:$D$27,$A6,'Team Data'!$G$2:$G$27,"No Audio Found on I3") -> 0 | H6: =IF(C6=0,0,D6/C6) -> 0.75 | I6: Communication / Soft Skills | J6: High | K6: Discovery & needs-based offers: listen to affordability concerns before pitching equipment/packages; no promises the fix will work. | L6: QA · Repeat (aiCR)
A7: bp-mammar838 | B7: Mohammed | C7: =COUNTIFS('Team Data'!$D$2:$D$27,A7) -> 5 | D7: =COUNTIFS('Team Data'!$D$2:$D$27,$A7,'Team Data'!$G$2:$G$27,"Agent Opportunity") -> 2 | E7: =COUNTIFS('Team Data'!$D$2:$D$27,$A7,'Team Data'!$G$2:$G$27,"Comcast Process/Tools") -> 3 | F7: =COUNTIFS('Team Data'!$D$2:$D$27,$A7,'Team Data'!$G$2:$G$27,"Customer") -> 0 | G7: =COUNTIFS('Team Data'!$D$2:$D$27,$A7,'Team Data'!$G$2:$G$27,"No Audio Found on I3") -> 0 | H7: =IF(C7=0,0,D7/C7) -> 0.4 | I7: Communication / Soft Skills | J7: High | K7: Validate outage/network status BEFORE diagnosing ("it's just you" was wrong); active listening on refusals; set pricing/promo expectations. | L7: QA · Repeat (aiCR)
A8: bp-mtadro821 | B8: — | C8: =COUNTIFS('Team Data'!$D$2:$D$27,A8) -> 2 | D8: =COUNTIFS('Team Data'!$D$2:$D$27,$A8,'Team Data'!$G$2:$G$27,"Agent Opportunity") -> 2 | E8: =COUNTIFS('Team Data'!$D$2:$D$27,$A8,'Team Data'!$G$2:$G$27,"Comcast Process/Tools") -> 0 | F8: =COUNTIFS('Team Data'!$D$2:$D$27,$A8,'Team Data'!$G$2:$G$27,"Customer") -> 0 | G8: =COUNTIFS('Team Data'!$D$2:$D$27,$A8,'Team Data'!$G$2:$G$27,"No Audio Found on I3") -> 0 | H8: =IF(C8=0,0,D8/C8) -> 1 | I8: Incorrect/ Incomplete Resolution | J8: High | K8: Resolve the primary reason first (payment extension) before offers; hold/mute etiquette — check in every 2 min. | L8: QA · Repeat (aiCR)
A9: bp-ahassa042 | B9: — | C9: =COUNTIFS('Team Data'!$D$2:$D$27,A9) -> 2 | D9: =COUNTIFS('Team Data'!$D$2:$D$27,$A9,'Team Data'!$G$2:$G$27,"Agent Opportunity") -> 1 | E9: =COUNTIFS('Team Data'!$D$2:$D$27,$A9,'Team Data'!$G$2:$G$27,"Comcast Process/Tools") -> 0 | F9: =COUNTIFS('Team Data'!$D$2:$D$27,$A9,'Team Data'!$G$2:$G$27,"Customer") -> 0 | G9: =COUNTIFS('Team Data'!$D$2:$D$27,$A9,'Team Data'!$G$2:$G$27,"No Audio Found on I3") -> 1 | H9: =IF(C9=0,0,D9/C9) -> 0.5 | I9: Ownership | J9: Medium | K9: Ownership: always call back after a dropped call. | L9: Repeat (aiCR)
A10: bp-maboel157 | B10: — | C10: =COUNTIFS('Team Data'!$D$2:$D$27,A10) -> 1 | D10: =COUNTIFS('Team Data'!$D$2:$D$27,$A10,'Team Data'!$G$2:$G$27,"Agent Opportunity") -> 1 | E10: =COUNTIFS('Team Data'!$D$2:$D$27,$A10,'Team Data'!$G$2:$G$27,"Comcast Process/Tools") -> 0 | F10: =COUNTIFS('Team Data'!$D$2:$D$27,$A10,'Team Data'!$G$2:$G$27,"Customer") -> 0 | G10: =COUNTIFS('Team Data'!$D$2:$D$27,$A10,'Team Data'!$G$2:$G$27,"No Audio Found on I3") -> 0 | H10: =IF(C10=0,0,D10/C10) -> 1 | I10: Communication / Soft Skills | J10: Medium | K10: Give the accurate root cause; do not position an upgrade as the fix for an outage. | L10: QA · Repeat (aiCR)
A11: bp-yawade572 | B11: Youssef | C11: =COUNTIFS('Team Data'!$D$2:$D$27,A11) -> 2 | D11: =COUNTIFS('Team Data'!$D$2:$D$27,$A11,'Team Data'!$G$2:$G$27,"Agent Opportunity") -> 1 | E11: =COUNTIFS('Team Data'!$D$2:$D$27,$A11,'Team Data'!$G$2:$G$27,"Comcast Process/Tools") -> 1 | F11: =COUNTIFS('Team Data'!$D$2:$D$27,$A11,'Team Data'!$G$2:$G$27,"Customer") -> 0 | G11: =COUNTIFS('Team Data'!$D$2:$D$27,$A11,'Team Data'!$G$2:$G$27,"No Audio Found on I3") -> 0 | H11: =IF(C11=0,0,D11/C11) -> 0.5 | I11: Communication / Soft Skills | J11: Medium | K11: Before transferring a frustrated repeat caller: empathy first, explain why and where the call is going (warm transfer). | L11: Transfer · QA
A12: bp-aelshe876 | B12: Amr | C12: =COUNTIFS('Team Data'!$D$2:$D$27,A12) -> 4 | D12: =COUNTIFS('Team Data'!$D$2:$D$27,$A12,'Team Data'!$G$2:$G$27,"Agent Opportunity") -> 1 | E12: =COUNTIFS('Team Data'!$D$2:$D$27,$A12,'Team Data'!$G$2:$G$27,"Comcast Process/Tools") -> 0 | F12: =COUNTIFS('Team Data'!$D$2:$D$27,$A12,'Team Data'!$G$2:$G$27,"Customer") -> 3 | G12: =COUNTIFS('Team Data'!$D$2:$D$27,$A12,'Team Data'!$G$2:$G$27,"No Audio Found on I3") -> 0 | H12: =IF(C12=0,0,D12/C12) -> 0.25 | I12: Excessive Hold/Mute | J12: Low | K12: Recognise: customers praised his patience. One fix: keep the customer updated while working with back office (no long silence). | L12: QA
A13: bp-jsolim238 | B13: Jana | C13: =COUNTIFS('Team Data'!$D$2:$D$27,A13) -> 1 | D13: =COUNTIFS('Team Data'!$D$2:$D$27,$A13,'Team Data'!$G$2:$G$27,"Agent Opportunity") -> 0 | E13: =COUNTIFS('Team Data'!$D$2:$D$27,$A13,'Team Data'!$G$2:$G$27,"Comcast Process/Tools") -> 0 | F13: =COUNTIFS('Team Data'!$D$2:$D$27,$A13,'Team Data'!$G$2:$G$27,"Customer") -> 1 | G13: =COUNTIFS('Team Data'!$D$2:$D$27,$A13,'Team Data'!$G$2:$G$27,"No Audio Found on I3") -> 0 | H13: =IF(C13=0,0,D13/C13) -> 0 | I13: — | J13: Low | K13: Detractor was a prior agent's miss. Tip: give a clear, structured plan for unresolved refunds instead of general reassurance. | L13: Repeat (aiCR)
A14: bp-aali048 | B14: — | C14: =COUNTIFS('Team Data'!$D$2:$D$27,A14) -> 1 | D14: =COUNTIFS('Team Data'!$D$2:$D$27,$A14,'Team Data'!$G$2:$G$27,"Agent Opportunity") -> 0 | E14: =COUNTIFS('Team Data'!$D$2:$D$27,$A14,'Team Data'!$G$2:$G$27,"Comcast Process/Tools") -> 1 | F14: =COUNTIFS('Team Data'!$D$2:$D$27,$A14,'Team Data'!$G$2:$G$27,"Customer") -> 0 | G14: =COUNTIFS('Team Data'!$D$2:$D$27,$A14,'Team Data'!$G$2:$G$27,"No Audio Found on I3") -> 0 | H14: =IF(C14=0,0,D14/C14) -> 0 | I14: — | J14: None | K14: Non-controllable (outage); comment notes good empathy. Recognise. | L14: —
A15: bp-mmahmo022 | B15: — | C15: =COUNTIFS('Team Data'!$D$2:$D$27,A15) -> 1 | D15: =COUNTIFS('Team Data'!$D$2:$D$27,$A15,'Team Data'!$G$2:$G$27,"Agent Opportunity") -> 0 | E15: =COUNTIFS('Team Data'!$D$2:$D$27,$A15,'Team Data'!$G$2:$G$27,"Comcast Process/Tools") -> 0 | F15: =COUNTIFS('Team Data'!$D$2:$D$27,$A15,'Team Data'!$G$2:$G$27,"Customer") -> 0 | G15: =COUNTIFS('Team Data'!$D$2:$D$27,$A15,'Team Data'!$G$2:$G$27,"No Audio Found on I3") -> 1 | H15: =IF(C15=0,0,D15/C15) -> 0 | I15: — | J15: None | K15: No audio — no assessment possible. | L15: —
A16: bp-okamel106 | B16: Omar | C16: =COUNTIFS('Team Data'!$D$2:$D$27,A16) -> 2 | D16: =COUNTIFS('Team Data'!$D$2:$D$27,$A16,'Team Data'!$G$2:$G$27,"Agent Opportunity") -> 0 | E16: =COUNTIFS('Team Data'!$D$2:$D$27,$A16,'Team Data'!$G$2:$G$27,"Comcast Process/Tools") -> 2 | F16: =COUNTIFS('Team Data'!$D$2:$D$27,$A16,'Team Data'!$G$2:$G$27,"Customer") -> 0 | G16: =COUNTIFS('Team Data'!$D$2:$D$27,$A16,'Team Data'!$G$2:$G$27,"No Audio Found on I3") -> 0 | H16: =IF(C16=0,0,D16/C16) -> 0 | I16: — | J16: None | K16: Non-controllable (tech/wiring, authentication). Recognise. | L16: —
A17: bp-yabdel208 | B17: Youssef | C17: =COUNTIFS('Team Data'!$D$2:$D$27,A17) -> 1 | D17: =COUNTIFS('Team Data'!$D$2:$D$27,$A17,'Team Data'!$G$2:$G$27,"Agent Opportunity") -> 0 | E17: =COUNTIFS('Team Data'!$D$2:$D$27,$A17,'Team Data'!$G$2:$G$27,"Comcast Process/Tools") -> 1 | F17: =COUNTIFS('Team Data'!$D$2:$D$27,$A17,'Team Data'!$G$2:$G$27,"Customer") -> 0 | G17: =COUNTIFS('Team Data'!$D$2:$D$27,$A17,'Team Data'!$G$2:$G$27,"No Audio Found on I3") -> 0 | H17: =IF(C17=0,0,D17/C17) -> 0 | I17: — | J17: None | K17: Non-controllable (repeated service failures). Recognise. | L17: —
A18: TEAM TOTAL | C18: =SUM(C6:C17) -> 26 | D18: =SUM(D6:D17) -> 11 | E18: =SUM(E6:E17) -> 9 | F18: =SUM(F6:F17) -> 4 | G18: =SUM(G6:G17) -> 2 | H18: =D18/C18 -> 0.42307692
A20: Yellow cells = fill in (assign each agent to one of your 3 team leaders; mark Coached? Yes/No/Scheduled). Agent names are taken from scrub comments where mentioned; Main Driver, Priority and Coaching Action written from the scrub evidence.

Sheet Day over Day
A1: My Team — Day over Day
A2: By Survey Date (the day the customer was surveyed) · 25-Sep → 06-Oct-2026
A5: Survey Date | B5: Surveys | C5: Agent Opp | D5: Comcast | E5: Customer | F5: No Audio | G5: Agent Opp % | H5: DoD Δ Surveys | I5: DoD Δ Agent Opp | J5: Agents with AO
A6: 46301 | B6: =COUNTIFS('Team Data'!$C$2:$C$27,$A6) -> 5 | C6: =COUNTIFS('Team Data'!$C$2:$C$27,$A6,'Team Data'!$G$2:$G$27,"Agent Opportunity") -> 1 | D6: =COUNTIFS('Team Data'!$C$2:$C$27,$A6,'Team Data'!$G$2:$G$27,"Comcast Process/Tools") -> 2 | E6: =COUNTIFS('Team Data'!$C$2:$C$27,$A6,'Team Data'!$G$2:$G$27,"Customer") -> 0 | F6: =COUNTIFS('Team Data'!$C$2:$C$27,$A6,'Team Data'!$G$2:$G$27,"No Audio Found on I3") -> 2 | G6: =IF(B6=0,"-",C6/B6) -> 0.2 | H6: =B6-B7 -> 2 | I6: =C6-C7 -> -1 | J6: bp-mtadro821
A7: 46300 | B7: =COUNTIFS('Team Data'!$C$2:$C$27,$A7) -> 3 | C7: =COUNTIFS('Team Data'!$C$2:$C$27,$A7,'Team Data'!$G$2:$G$27,"Agent Opportunity") -> 2 | D7: =COUNTIFS('Team Data'!$C$2:$C$27,$A7,'Team Data'!$G$2:$G$27,"Comcast Process/Tools") -> 1 | E7: =COUNTIFS('Team Data'!$C$2:$C$27,$A7,'Team Data'!$G$2:$G$27,"Customer") -> 0 | F7: =COUNTIFS('Team Data'!$C$2:$C$27,$A7,'Team Data'!$G$2:$G$27,"No Audio Found on I3") -> 0 | G7: =IF(B7=0,"-",C7/B7) -> 0.66666667 | H7: =B7-B8 -> 2 | I7: =C7-C8 -> 1 | J7: bp-ahassa042, bp-akahal350
A8: 46299 | B8: =COUNTIFS('Team Data'!$C$2:$C$27,$A8) -> 1 | C8: =COUNTIFS('Team Data'!$C$2:$C$27,$A8,'Team Data'!$G$2:$G$27,"Agent Opportunity") -> 1 | D8: =COUNTIFS('Team Data'!$C$2:$C$27,$A8,'Team Data'!$G$2:$G$27,"Comcast Process/Tools") -> 0 | E8: =COUNTIFS('Team Data'!$C$2:$C$27,$A8,'Team Data'!$G$2:$G$27,"Customer") -> 0 | F8: =COUNTIFS('Team Data'!$C$2:$C$27,$A8,'Team Data'!$G$2:$G$27,"No Audio Found on I3") -> 0 | G8: =IF(B8=0,"-",C8/B8) -> 1 | H8: =B8-B9 -> 0 | I8: =C8-C9 -> 1 | J8: bp-aelshe876
A9: 46298 | B9: =COUNTIFS('Team Data'!$C$2:$C$27,$A9) -> 1 | C9: =COUNTIFS('Team Data'!$C$2:$C$27,$A9,'Team Data'!$G$2:$G$27,"Agent Opportunity") -> 0 | D9: =COUNTIFS('Team Data'!$C$2:$C$27,$A9,'Team Data'!$G$2:$G$27,"Comcast Process/Tools") -> 0 | E9: =COUNTIFS('Team Data'!$C$2:$C$27,$A9,'Team Data'!$G$2:$G$27,"Customer") -> 1 | F9: =COUNTIFS('Team Data'!$C$2:$C$27,$A9,'Team Data'!$G$2:$G$27,"No Audio Found on I3") -> 0 | G9: =IF(B9=0,"-",C9/B9) -> 0 | H9: =B9-B10 -> 0 | I9: =C9-C10 -> 0 | J9: —
A10: 46297 | B10: =COUNTIFS('Team Data'!$C$2:$C$27,$A10) -> 1 | C10: =COUNTIFS('Team Data'!$C$2:$C$27,$A10,'Team Data'!$G$2:$G$27,"Agent Opportunity") -> 0 | D10: =COUNTIFS('Team Data'!$C$2:$C$27,$A10,'Team Data'!$G$2:$G$27,"Comcast Process/Tools") -> 1 | E10: =COUNTIFS('Team Data'!$C$2:$C$27,$A10,'Team Data'!$G$2:$G$27,"Customer") -> 0 | F10: =COUNTIFS('Team Data'!$C$2:$C$27,$A10,'Team Data'!$G$2:$G$27,"No Audio Found on I3") -> 0 | G10: =IF(B10=0,"-",C10/B10) -> 0 | H10: =B10-B11 -> -3 | I10: =C10-C11 -> -2 | J10: —
A11: 46296 | B11: =COUNTIFS('Team Data'!$C$2:$C$27,$A11) -> 4 | C11: =COUNTIFS('Team Data'!$C$2:$C$27,$A11,'Team Data'!$G$2:$G$27,"Agent Opportunity") -> 2 | D11: =COUNTIFS('Team Data'!$C$2:$C$27,$A11,'Team Data'!$G$2:$G$27,"Comcast Process/Tools") -> 2 | E11: =COUNTIFS('Team Data'!$C$2:$C$27,$A11,'Team Data'!$G$2:$G$27,"Customer") -> 0 | F11: =COUNTIFS('Team Data'!$C$2:$C$27,$A11,'Team Data'!$G$2:$G$27,"No Audio Found on I3") -> 0 | G11: =IF(B11=0,"-",C11/B11) -> 0.5 | H11: =B11-B12 -> 2 | I11: =C11-C12 -> 1 | J11: bp-akahal350, bp-mammar838
A12: 46295 | B12: =COUNTIFS('Team Data'!$C$2:$C$27,$A12) -> 2 | C12: =COUNTIFS('Team Data'!$C$2:$C$27,$A12,'Team Data'!$G$2:$G$27,"Agent Opportunity") -> 1 | D12: =COUNTIFS('Team Data'!$C$2:$C$27,$A12,'Team Data'!$G$2:$G$27,"Comcast Process/Tools") -> 1 | E12: =COUNTIFS('Team Data'!$C$2:$C$27,$A12,'Team Data'!$G$2:$G$27,"Customer") -> 0 | F12: =COUNTIFS('Team Data'!$C$2:$C$27,$A12,'Team Data'!$G$2:$G$27,"No Audio Found on I3") -> 0 | G12: =IF(B12=0,"-",C12/B12) -> 0.5 | H12: =B12-B13 -> 1 | I12: =C12-C13 -> 1 | J12: bp-yawade572
A13: 46294 | B13: =COUNTIFS('Team Data'!$C$2:$C$27,$A13) -> 1 | C13: =COUNTIFS('Team Data'!$C$2:$C$27,$A13,'Team Data'!$G$2:$G$27,"Agent Opportunity") -> 0 | D13: =COUNTIFS('Team Data'!$C$2:$C$27,$A13,'Team Data'!$G$2:$G$27,"Comcast Process/Tools") -> 1 | E13: =COUNTIFS('Team Data'!$C$2:$C$27,$A13,'Team Data'!$G$2:$G$27,"Customer") -> 0 | F13: =COUNTIFS('Team Data'!$C$2:$C$27,$A13,'Team Data'!$G$2:$G$27,"No Audio Found on I3") -> 0 | G13: =IF(B13=0,"-",C13/B13) -> 0 | H13: =B13-B14 -> -3 | I13: =C13-C14 -> -2 | J13: —
A14: 46293 | B14: =COUNTIFS('Team Data'!$C$2:$C$27,$A14) -> 4 | C14: =COUNTIFS('Team Data'!$C$2:$C$27,$A14,'Team Data'!$G$2:$G$27,"Agent Opportunity") -> 2 | D14: =COUNTIFS('Team Data'!$C$2:$C$27,$A14,'Team Data'!$G$2:$G$27,"Comcast Process/Tools") -> 1 | E14: =COUNTIFS('Team Data'!$C$2:$C$27,$A14,'Team Data'!$G$2:$G$27,"Customer") -> 1 | F14: =COUNTIFS('Team Data'!$C$2:$C$27,$A14,'Team Data'!$G$2:$G$27,"No Audio Found on I3") -> 0 | G14: =IF(B14=0,"-",C14/B14) -> 0.5 | H14: =B14-B15 -> 2 | I14: =C14-C15 -> 2 | J14: bp-mammar838, bp-mtadro821
A15: 46292 | B15: =COUNTIFS('Team Data'!$C$2:$C$27,$A15) -> 2 | C15: =COUNTIFS('Team Data'!$C$2:$C$27,$A15,'Team Data'!$G$2:$G$27,"Agent Opportunity") -> 0 | D15: =COUNTIFS('Team Data'!$C$2:$C$27,$A15,'Team Data'!$G$2:$G$27,"Comcast Process/Tools") -> 0 | E15: =COUNTIFS('Team Data'!$C$2:$C$27,$A15,'Team Data'!$G$2:$G$27,"Customer") -> 2 | F15: =COUNTIFS('Team Data'!$C$2:$C$27,$A15,'Team Data'!$G$2:$G$27,"No Audio Found on I3") -> 0 | G15: =IF(B15=0,"-",C15/B15) -> 0 | H15: =B15-B16 -> 1 | I15: =C15-C16 -> -1 | J15: —
A16: 46291 | B16: =COUNTIFS('Team Data'!$C$2:$C$27,$A16) -> 1 | C16: =COUNTIFS('Team Data'!$C$2:$C$27,$A16,'Team Data'!$G$2:$G$27,"Agent Opportunity") -> 1 | D16: =COUNTIFS('Team Data'!$C$2:$C$27,$A16,'Team Data'!$G$2:$G$27,"Comcast Process/Tools") -> 0 | E16: =COUNTIFS('Team Data'!$C$2:$C$27,$A16,'Team Data'!$G$2:$G$27,"Customer") -> 0 | F16: =COUNTIFS('Team Data'!$C$2:$C$27,$A16,'Team Data'!$G$2:$G$27,"No Audio Found on I3") -> 0 | G16: =IF(B16=0,"-",C16/B16) -> 1 | H16: =B16-B17 -> 0 | I16: =C16-C17 -> 0 | J16: bp-akahal350
A17: 46290 | B17: =COUNTIFS('Team Data'!$C$2:$C$27,$A17) -> 1 | C17: =COUNTIFS('Team Data'!$C$2:$C$27,$A17,'Team Data'!$G$2:$G$27,"Agent Opportunity") -> 1 | D17: =COUNTIFS('Team Data'!$C$2:$C$27,$A17,'Team Data'!$G$2:$G$27,"Comcast Process/Tools") -> 0 | E17: =COUNTIFS('Team Data'!$C$2:$C$27,$A17,'Team Data'!$G$2:$G$27,"Customer") -> 0 | F17: =COUNTIFS('Team Data'!$C$2:$C$27,$A17,'Team Data'!$G$2:$G$27,"No Audio Found on I3") -> 0 | G17: =IF(B17=0,"-",C17/B17) -> 1 | H17: =0 -> 0 | I17: =0 -> 0 | J17: bp-maboel157
A18: TOTAL | B18: =SUM(B6:B17) -> 26 | C18: =SUM(C6:C17) -> 11 | D18: =SUM(D6:D17) -> 9 | E18: =SUM(E6:E17) -> 4 | F18: =SUM(F6:F17) -> 2 | G18: =C18/B18 -> 0.42307692
A19: Survey Date used (not scrub date) because all team scrubs were submitted on only 3 days. Δ in red = more detractors than the day before. "Agents with AO" computed in Python.

Sheet Coaching Log
A1: My Team — Coaching Log (Agent Opportunity detractors)
A2: One row per controllable detractor · evidence from the scrub · yellow = fill in
A5: BPID | B5: Agent | C5: Survey ID | D5: Survey Date | E5: RCA T2 | F5: Scrub Evidence | G5: Behaviour to Coach | H5: Team Leader | I5: Coaching Date | J5: Agent Commitment | K5: Follow-up Date | L5: Status
A6: bp-akahal350 | B6: Ahmed | C6: 2194198617 | D6: 46291 | E6: Communication / Soft Skills | F6: Pure Handling Skills | G6: Active listening, empathy & reassurance; acknowledge concern before solutioning | K6: =IF(I6="","",I6+14)
A7: bp-akahal350 | B7: Ahmed | C7: 2196171839 | D7: 46296 | E7: Knowledge Gap | F7: Discovery / Identifying Customer Needs / Offering Relevant Solutions | G7: Discovery questions → needs-based solution | K7: =IF(I7="","",I7+14)
A8: bp-akahal350 | B8: Ahmed | C8: 2197295862 | D8: 46300 | E8: Communication / Soft Skills | F8: The customer wanted reliable internet without another significant price increase. Ahmed concentrated on presenting equipment and package solutions while the customer continued expressing concerns about affordability and whether the changes would actually work. One important distinction: the existing internet problems and price increases were Comcast-driven, but Ahmed's communication, diagnosis, and promises were controllable | G8: Active listening, empathy & reassurance; acknowledge concern before solutioning | K8: =IF(I8="","",I8+14)
A9: bp-mammar838 | B9: Mohammed | C9: 2194926007 | D9: 46293 | E9: Communication / Soft Skills | F9: Controllable — because Mohammed controlled whether he listened to the customer's repeated refusal, kept the interaction focused on the TV issue, and explained the troubleshooting steps clearly. | G9: Active listening, empathy & reassurance; acknowledge concern before solutioning | K9: =IF(I9="","",I9+14)
A10: bp-mammar838 | B10: Mohammed | C10: 2196122081 | D10: 46296 | E10: Communication / Soft Skills | F10: HSD Repair - Controllable — not because the agent controlled the available pricing, but because empathy, expectation-setting, and clarity around promotional eligibility could have been stronger. | G10: Active listening, empathy & reassurance; acknowledge concern before solutioning | K10: =IF(I10="","",I10+14)
A11: bp-mtadro821 | C11: 2194889759 | D11: 46293 | E11: Incorrect/ Incomplete Resolution | F11: the customer called to protect her service while delaying payment until October 10, but the conversation became centered on changing her plan and additional offers before that core concern was clearly and safely resolved. | G11: Resolve primary reason first; confirm resolution before offers | K11: =IF(I11="","",I11+14)
A12: bp-mtadro821 | C12: 2197495330 | D12: 46301 | E12: Excessive Hold/Mute | F12: Excessive Hold/Mute, Customer Education – Setting Expectations, Communication / Rapport | G12: Hold etiquette: ask permission, check in every 2 min, no silent gaps | K12: =IF(I12="","",I12+14)
A13: bp-ahassa042 | C13: 2197465776 | D13: 46300 | E13: Ownership | F13: Call got disconnected and the customer was never called back | G13: Own the call end-to-end; call back after a disconnect | K13: =IF(I13="","",I13+14)
A14: bp-maboel157 | C14: 30003055651790377517 | D14: 46290 | E14: Communication / Soft Skills | F14: Customer contacted regarding internet being disconnected for approximately 3 days. Agent verified the account and completed troubleshooting, and the connection was restored. However, during troubleshooting, the agent advised that the likely cause of the issue was the customer being on a legacy package and stated that upgrading to a next-generation package would help avoid future outages. This was not supported by the interaction, especially since the customer mentioned recent repair work in the area and service was restored through troubleshooting. The sales positioning created additional dissatisfaction around pricing. Classified as Agent Opportunity – Incorrect/Incomplete Resolution. | G14: Active listening, empathy & reassurance; acknowledge concern before solutioning | K14: =IF(I14="","",I14+14)
A15: bp-yawade572 | B15: Youssef | C15: 2195770811 | D15: 46295 | E15: Communication / Soft Skills | F15: he made the correct decision to route the customer, but with a repeat-contact customer this frustrated, the experience needs stronger empathy upfront and a much clearer explanation of exactly what is happening before another transfer. | G15: Active listening, empathy & reassurance; acknowledge concern before solutioning | K15: =IF(I15="","",I15+14)
A16: bp-aelshe876 | B16: Amr | C16: 2197129523 | D16: 46299 | E16: Excessive Hold/Mute | F16: Amr demonstrated good empathy and reassurance early in the call. The customer clearly felt heard initially, and Amr explained what troubleshooting he was performing. The problem was ownership throughout the full interaction. Once Amr went to work with the back office, the customer was left without communication. Regardless of whether Amr was muted, researching, or experiencing another issue, the customer experienced several minutes of silence and ultimately believed he had been abandoned. So the controllability is not because Amr lacked empathy throughout the entire call. It is because he failed to maintain ownership, communication, and reassurance until the interaction was completed. | G16: Hold etiquette: ask permission, check in every 2 min, no silent gaps | K16: =IF(I16="","",I16+14)
A18: Follow-up Date = Coaching Date + 14 days (assumption: 2-week re-check). Status options: Open / Coached / Improved / Repeat.

Sheet Team Data
A1: Data ID | B1: Scrub Date | C1: Survey Date | D1: BPID | E1: Agent (from comment) | F1: Survey ID | G1: RCA | H1: RCA T2 | I1: Comment | J1: Scrubber
A2: 2238 | B2: 46294 | C2: 46290 | D2: bp-maboel157 | F2: 30003055651790377517 | G2: Agent Opportunity | H2: Communication / Soft Skills | I2: Customer contacted regarding internet being disconnected for approximately 3 days. Agent verified the account and completed troubleshooting, and the connection was restored. However, during troubleshooting, the agent advised that the likely cause of the issue was the customer being on a legacy package and stated that upgrading to a next-generation package would help avoid future outages. This was not supported by the interaction, especially since the customer mentioned recent repair work in the area and service was restored through troubleshooting. The sales positioning created additional dissatisfaction around pricing. Classified as Agent Opportunity – Incorrect/Incomplete Resolution. | J2: Omar Mansour (Omar Ali Mohamed)
A3: 2295 | B3: 46301 | C3: 46297 | D3: bp-mammar838 | E3: Mohammed | F3: 2196550037 | G3: Comcast Process/Tools | H3: Dissatisfied with service | I3: Customer contacted regarding persistent network/connectivity issues and stated the problem had been ongoing for several months. Customer expressed significant dissatisfaction with the quality of service and advised that she may change providers if the issue continues. Agent attempted multiple account verification methods; however, the account was under the customer's husband and the customer was unable to complete verification through the account holder, payment card, or registered email. As a result, the agent was unable to proceed with account-level troubleshooting. Primary detractor driver was the customer's ongoing dissatisfaction with the network/service rather than an agent-created issue. | J3: Omar Mansour (Omar Ali Mohamed)
A4: 2296 | B4: 46301 | C4: 46296 | D4: bp-mammar838 | E4: Mohammed | F4: 2196122081 | G4: Agent Opportunity | H4: Communication / Soft Skills | I4: HSD Repair - Controllable — not because the agent controlled the available pricing, but because empathy, expectation-setting, and clarity around promotional eligibility could have been stronger. | J4: Omar Mansour (Omar Ali Mohamed)
A5: 2299 | B5: 46301 | C5: 46296 | D5: bp-mammar838 | E5: Mohammed | F5: 2196030751 | G5: Comcast Process/Tools | H5: Outage | I5: The customer contacted because Comcast work in the area caused a service interruption and she was frustrated that she did not believe she had been notified. Once Mohammed accessed the account, he identified an outage notification and provided an estimated restoration time of approximately 4:40 PM. The outage itself was outside the agent's control. | J5: Omar Mansour (Omar Ali Mohamed)
A6: 2327 | B6: 46301 | C6: 46294 | D6: bp-mammar838 | E6: Mohammed | F6: 2195165826 | G6: Comcast Process/Tools | H6: Outage | I6: The customer called because her internet had just gone down and immediately asked whether the issue was on Comcast’s side. Mohammed told her, without validating first, that “unfortunately, it’s just you” and suggested it was probably a signal issue. Later in the same call, the customer received an Xfinity notification confirming that service was unavailable due to an issue with the Comcast network. | J6: Omar Mansour (Omar Ali Mohamed)
A7: 2330 | B7: 46301 | C7: 46293 | D7: bp-mammar838 | E7: Mohammed | F7: 2194926007 | G7: Agent Opportunity | H7: Communication / Soft Skills | I7: Controllable — because Mohammed controlled whether he listened to the customer's repeated refusal, kept the interaction focused on the TV issue, and explained the troubleshooting steps clearly. | J7: Omar Mansour (Omar Ali Mohamed)
A8: 2341 | B8: 46301 | C8: 46299 | D8: bp-aelshe876 | E8: Amr | F8: 2197129523 | G8: Agent Opportunity | H8: Excessive Hold/Mute | I8: Amr demonstrated good empathy and reassurance early in the call. The customer clearly felt heard initially, and Amr explained what troubleshooting he was performing. The problem was ownership throughout the full interaction. Once Amr went to work with the back office, the customer was left without communication. Regardless of whether Amr was muted, researching, or experiencing another issue, the customer experienced several minutes of silence and ultimately believed he had been abandoned. So the controllability is not because Amr lacked empathy throughout the entire call. It is because he failed to maintain ownership, communication, and reassurance until the interaction was completed. | J8: Omar Mansour (Omar Ali Mohamed)
A9: 2342 | B9: 46301 | C9: 46298 | D9: bp-aelshe876 | E9: Amr | F9: 2196814455 | G9: Customer | H9: Another Agent's Opportunity | I9: during the interaction, the customer explicitly contrasted Amr with the previous experience and told him: “Sonya screwed me over here… you’re doing everything perfect. I give you an 8 now. | J9: Omar Mansour (Omar Ali Mohamed)
A10: 2344 | B10: 46301 | C10: 46293 | D10: bp-aelshe876 | E10: Amr | F10: 2195342301 | G10: Customer | H10: Customer Provided the agent positive feedback | I10: Amr first helped the customer regain access to the account by walking him through the password-reset and verification process. The customer was clearly struggling with the technology, but Amr stayed with him through the process. During that portion, the customer explicitly told Amr: “You’re nice man. You’re very patient. | J10: Omar Mansour (Omar Ali Mohamed)
A11: 2345 | B11: 46301 | C11: 46292 | D11: bp-aelshe876 | E11: Amr | F11: 2194689303 | G11: Customer | H11: Customer Provided the agent positive feedback | I11: The customer's reaction was positive—she responded, “Oh wonderful. Why didn't somebody do that a long time ago.” That statement reinforces that her frustration was with what had happened before reaching Amr, not with his handling. | J11: Omar Mansour (Omar Ali Mohamed)
A12: 2349 | B12: 46301 | C12: 46293 | D12: bp-mtadro821 | F12: 2194889759 | G12: Agent Opportunity | H12: Incorrect/ Incomplete Resolution | I12: the customer called to protect her service while delaying payment until October 10, but the conversation became centered on changing her plan and additional offers before that core concern was clearly and safely resolved. | J12: Omar Mansour (Omar Ali Mohamed)
A13: 2352 | B13: 46301 | C13: 46292 | D13: bp-jsolim238 | E13: Jana | F13: 2194816382 | G13: Customer | H13: Another Agent's Opportunity | I13: he customer came in dissatisfied because of the unresolved refund, while Jana's opportunity was to make the current interaction feel more structured, more transparent, and less like the same vague reassurance he had already received from previous agents. | J13: Omar Mansour (Omar Ali Mohamed)
A14: 2360 | B14: 46301 | C14: 46296 | D14: bp-yawade572 | E14: Youssef | F14: 2196196507 | G14: Comcast Process/Tools | H14: Comcast Restriction (add on the comment which Restriction) | I14: The customer contacted Xfinity because he could not access Wi-Fi. Youssef checked the account and identified the actual reason quickly: the account had been soft disconnected because of a $192.32 past-due balance. He then clearly explained that the Wi-Fi could not be restored until the payment was made. The customer understood the explanation and essentially accepted the situation: “Okay got it… what I’ll do that then I’ll call you.” There is no strong indication that the customer became frustrated specifically because of Youssef. | J14: Omar Mansour (Omar Ali Mohamed)
A15: 2363 | B15: 46301 | C15: 46295 | D15: bp-yawade572 | E15: Youssef | F15: 2195770811 | G15: Agent Opportunity | H15: Communication / Soft Skills | I15: he made the correct decision to route the customer, but with a repeat-contact customer this frustrated, the experience needs stronger empathy upfront and a much clearer explanation of exactly what is happening before another transfer. | J15: Omar Mansour (Omar Ali Mohamed)
A16: 2440 | B16: 46302 | C16: 46301 | D16: bp-mtadro821 | F16: 2197495330 | G16: Agent Opportunity | H16: Excessive Hold/Mute | I16: Excessive Hold/Mute, Customer Education – Setting Expectations, Communication / Rapport | J16: Omar Mansour (Omar Ali Mohamed)
A17: 2442 | B17: 46302 | C17: 46300 | D17: bp-akahal350 | E17: Ahmed | F17: 2197295862 | G17: Agent Opportunity | H17: Communication / Soft Skills | I17: The customer wanted reliable internet without another significant price increase. Ahmed concentrated on presenting equipment and package solutions while the customer continued expressing concerns about affordability and whether the changes would actually work. One important distinction: the existing internet problems and price increases were Comcast-driven, but Ahmed's communication, diagnosis, and promises were controllable | J17: Omar Mansour (Omar Ali Mohamed)
A18: 2443 | B18: 46302 | C18: 46296 | D18: bp-akahal350 | E18: Ahmed | F18: 2196171839 | G18: Agent Opportunity | H18: Knowledge Gap | I18: Discovery / Identifying Customer Needs / Offering Relevant Solutions | J18: Omar Mansour (Omar Ali Mohamed)
A19: 2480 | B19: 46302 | C19: 46293 | D19: bp-akahal350 | E19: Ahmed | F19: 2195162416 | G19: Comcast Process/Tools | H19: Complaints about the technician | I19: Technician Scheduling | J19: Omar Mansour (Omar Ali Mohamed)
A20: 2481 | B20: 46302 | C20: 46291 | D20: bp-akahal350 | E20: Ahmed | F20: 2194198617 | G20: Agent Opportunity | H20: Communication / Soft Skills | I20: Pure Handling Skills | J20: Omar Mansour (Omar Ali Mohamed)
A21: 2482 | B21: 46302 | C21: 46301 | D21: bp-yabdel208 | E21: Youssef | F21: 2197847600 | G21: Comcast Process/Tools | H21: Dissatisfied with service | I21: They had already received approximately their fourth replacement box, the internet had been cutting out multiple times every day for months, technicians had repeatedly visited the home, equipment had been replaced, and wiring had been worked on without a lasting fix. Pasted text The customer then told Youssef: technicians keep coming out and nothing gets fixed. | J21: Omar Mansour (Omar Ali Mohamed)
A22: 2483 | B22: 46302 | C22: 46301 | D22: bp-mmahmo022 | F22: 2197860585 | G22: No Audio Found on I3 | J22: Omar Mansour (Omar Ali Mohamed)
A23: 2485 | B23: 46302 | C23: 46301 | D23: bp-ahassa042 | F23: 2197808496 | G23: No Audio Found on I3 | J23: Omar Mansour (Omar Ali Mohamed)
A24: 2486 | B24: 46302 | C24: 46300 | D24: bp-ahassa042 | F24: 2197465776 | G24: Agent Opportunity | H24: Ownership | I24: Call got disconnected and the customer was never called back | J24: Omar Mansour (Omar Ali Mohamed)
A25: 2487 | B25: 46302 | C25: 46301 | D25: bp-okamel106 | E25: Omar | F25: 2197421005 | G25: Comcast Process/Tools | H25: Dissatisfied with service | I25: The customer's original problem was a complete loss of internet/TV service. Omar's diagnostics pointed toward a coax/wiring issue requiring a technician. That technical failure existed before Omar handled the interaction. | J25: Omar Mansour (Omar Ali Mohamed)
A26: 2488 | B26: 46302 | C26: 46295 | D26: bp-okamel106 | E26: Omar | F26: 2195718905 | G26: Comcast Process/Tools | H26: Comcast Restriction (add on the comment which Restriction) | I26: Customer could not authentication | J26: Omar Mansour (Omar Ali Mohamed)
A27: 2489 | B27: 46302 | C27: 46300 | D27: bp-aali048 | F27: 2197341018 | G27: Comcast Process/Tools | H27: Outage | I27: Agent was friendly assured help showed empathy yet the customer had an outage and was upset cuz of it | J27: Omar Mansour (Omar Ali Mohamed)
A30: Excluded rows (duplicate Survey ID — latest submission kept)
A31: 2422 | D31: bp-akahal350 | F31: 2196171839 | G31: Comcast Process/Tools | H31: Comcast Restriction (add on the comment which Restriction)
A32: 2484 | D32: bp-ahassa042 | F32: 2197808496 | G32: No Audio Found on I3
A34: Also excluded: test row ID 2030 (BPID "11"). BPID typo "p-aelshe876" corrected to bp-aelshe876. Team = the 12 BPIDs in Omar Mansour's scrubs.
