Workbook

Sheet Executive Summary
A1: NPS Scrubbing — Executive Summary
A2: VXI · Comcast · Scrub data 01-Apr → 07-Oct-2026 · 2,283 scrubs · 12 scrubbers
A5: Total Scrubs | C5: Agent Opp % | E5: Comcast % | G5: No Audio % | I5: Rows w/ Dup Survey ID | K5: Today (07-Oct) | M5: DoD Δ Volume
A6: =COUNTA(Data!$D$2:$D$2284) -> 2283 | C6: =COUNTIFS(Data!$H$2:$H$2284,"Agent Opportunity")/COUNTA(Data!$D$2:$D$2284) -> 0.63863338 | E6: =COUNTIFS(Data!$H$2:$H$2284,"Comcast Process/Tools")/COUNTA(Data!$D$2:$D$2284) -> 0.17564608 | G6: =COUNTIFS(Data!$H$2:$H$2284,"No Audio Found on I3")/COUNTA(Data!$D$2:$D$2284) -> 0.081909768 | I6: =COUNTIFS(Data!$L$2:$L$2284,"Y") -> 260 | K6: =COUNTIFS(Data!$B$2:$B$2284,DATE(2026,10,7)) -> 110 | M6: ='Day over Day'!K6 -> 26
A8: Key Insights — Account
A9: 1. VOLUME SPIKE: 07-Oct (110) and 06-Oct (84) are the two highest scrub days on record (prior peak 78 on 24-Aug) — backlog clearing; check whether quality held.
A10: 2. AGENT OPPORTUNITY = 64% of all detractors. Oct MTD is 56% vs 68% in Sep: 06-Oct dipped to 46% AO (Comcast 31%), 07-Oct recovered to 65% (+18 pts DoD).
A11: 3. "CALL HANDLING" is 41% of Agent Opp (596) — too generic to coach. Split it into specific behaviours; Communication/Soft Skills (24%) is #2, Knowledge Gap #3.
A12: 4. CALIBRATION GAP: scrubbers range from 21% AO (Anas) to 78% AO (Eslam). Same survey type, different verdicts → affects agent QA/NPS fairness.
A13: 5. DATA QUALITY: 260 rows share a Survey ID (133 extra copies); 36 surveys carry CONFLICTING RCAs; 36 rows with invalid BPID (numbers/typos); 81 blank Survey Dates; 6 Survey Dates in the future.
A14: 6. NO AUDIO = 8% (187 scrubs) — scrub effort with zero insight. Escalate I3 recording gaps to WFM/IT.
A15: 7. REPEAT DETRACTORS: bp-hawad742 (43 AO) and bp-gghane435 (42 AO) lead — top 10 BPIDs = 19% of all Agent Opp. Coaching focus for team leaders.
A16: 8. COMCAST drivers: Technician complaints (112) and Dissatisfied with service (158) — non-controllable but shareable with client as VOC.
A18: Key Insights — Omar Mansour (29 scrubs)
A19: • RCA mix skews non-controllable: Agent Opp 38% vs 64% account; Comcast 34% vs 18%. One Comcast-tagged call (ID 2120) shows agent misinformation → likely Agent Opp.
A20: • Accuracy: 4 of 29 rows (14%) are a test row ("11") or duplicates — one duplicate survey has two different RCAs.
... A32: Insight text written from the data at build time (07-Oct-2026); KPI tiles and all tables are live formulas on the Data tab.

Sheet Omar Mansour Review
A1: Scrubber Review — Omar Mansour
A2: Submitted as "Omar Ali Mohamed" · Omar.Mansour@vxi.com · 29 scrubs (29-Sep → 07-Oct-2026)
A5: Omar vs Account — KPIs
A6: KPI | B6: Omar | C6: Account | D6: Gap | E6: Read
A7: Total scrubs | B7: =COUNTIFS(Data!$D$2:$D$2284,"Omar.Mansour@vxi.com") -> 29 | C7: =COUNTA(Data!$D$2:$D$2284) -> 2283 | E7: Low volume — joined late Sep; 27 of 29 on 6–7 Oct
A8: Agent Opportunity % | B8: =COUNTIFS(Data!$D$2:$D$2284,"Omar.Mansour@vxi.com",Data!$H$2:$H$2284,"Agent Opportunity")/B7 -> 0.37931034 | C8: =COUNTIFS(Data!$H$2:$H$2284,"Agent Opportunity")/C7 -> 0.63863338 | D8: =(B8-C8)*100 -> -25.932303 | E8: Lowest AO% after Anas — leans to non-controllable
A9: Comcast Process/Tools % | B9: =COUNTIFS(Data!$D$2:$D$2284,"Omar.Mansour@vxi.com",Data!$H$2:$H$2284,"Comcast Process/Tools")/B7 -> 0.34482759 | C9: =COUNTIFS(Data!$H$2:$H$2284,"Comcast Process/Tools")/C7 -> 0.17564608 | D9: =(B9-C9)*100 -> 16.918151 | E9: ~2x account — validate each Comcast tag
A10: Customer % | B10: =COUNTIFS(Data!$D$2:$D$2284,"Omar.Mansour@vxi.com",Data!$H$2:$H$2284,"Customer")/B7 -> 0.13793103 | C10: =COUNTIFS(Data!$H$2:$H$2284,"Customer")/C7 -> 0.08935611 | D10: =(B10-C10)*100 -> 4.8574924 | E10: Higher; 2 are positive-feedback calls (good catch)
A11: No Audio % | B11: =COUNTIFS(Data!$D$2:$D$2284,"Omar.Mansour@vxi.com",Data!$H$2:$H$2284,"No Audio Found on I3")/B7 -> 0.13793103 | C11: =COUNTIFS(Data!$H$2:$H$2284,"No Audio Found on I3")/C7 -> 0.081909768 | D11: =(B11-C11)*100 -> 5.6021267 | E11: Includes 1 test row + 1 duplicate
A12: Rows sharing a Survey ID | B12: =COUNTIFS(Data!$D$2:$D$2284,"Omar.Mansour@vxi.com",Data!$L$2:$L$2284,"Y") -> 4 | C12: =COUNTIFS(Data!$L$2:$L$2284,"Y") -> 260 | D12: =B12/B7-C12/C7 -> 0.024045796 | E12: 2 surveys submitted twice
A13: Comment filled % | B13: =COUNTIFS(Data!$D$2:$D$2284,"Omar.Mansour@vxi.com",Data!$J$2:$J$2284,"<>")/B7 -> 0.86206897 | C13: =COUNTIFS(Data!$J$2:$J$2284,"<>")/C7 -> 0.91633815 | E13: All non-No-Audio rows have comments; richest narratives on account
A15: Omar — Day over Day
A16: Scrub Date | B16: Scrubs | C16: Agent Opp | D16: Comcast | E16: Customer | F16: No Audio | G16: AO %
A17: 46294 | B17: =COUNTIFS(Data!$D$2:$D$2284,"Omar.Mansour@vxi.com",Data!$B$2:$B$2284,A17) -> 2 | C17: =COUNTIFS(Data!$D$2:$D$2284,"Omar.Mansour@vxi.com",Data!$B$2:$B$2284,$A17,Data!$H$2:$H$2284,"Agent Opportunity") -> 1 | D17: =COUNTIFS(Data!$D$2:$D$2284,"Omar.Mansour@vxi.com",Data!$B$2:$B$2284,$A17,Data!$H$2:$H$2284,"Comcast Process/Tools") -> 0 | E17: =COUNTIFS(Data!$D$2:$D$2284,"Omar.Mansour@vxi.com",Data!$B$2:$B$2284,$A17,Data!$H$2:$H$2284,"Customer") -> 0 | F17: =COUNTIFS(Data!$D$2:$D$2284,"Omar.Mansour@vxi.com",Data!$B$2:$B$2284,$A17,Data!$H$2:$H$2284,"No Audio Found on I3") -> 1 | G17: =IF(B17=0,0,C17/B17) -> 0.5
A18: 46301 | B18: =COUNTIFS(Data!$D$2:$D$2284,"Omar.Mansour@vxi.com",Data!$B$2:$B$2284,A18) -> 13 | C18: =COUNTIFS(Data!$D$2:$D$2284,"Omar.Mansour@vxi.com",Data!$B$2:$B$2284,$A18,Data!$H$2:$H$2284,"Agent Opportunity") -> 5 | D18: =COUNTIFS(Data!$D$2:$D$2284,"Omar.Mansour@vxi.com",Data!$B$2:$B$2284,$A18,Data!$H$2:$H$2284,"Comcast Process/Tools") -> 4 | E18: =COUNTIFS(Data!$D$2:$D$2284,"Omar.Mansour@vxi.com",Data!$B$2:$B$2284,$A18,Data!$H$2:$H$2284,"Customer") -> 4 | F18: =COUNTIFS(Data!$D$2:$D$2284,"Omar.Mansour@vxi.com",Data!$B$2:$B$2284,$A18,Data!$H$2:$H$2284,"No Audio Found on I3") -> 0 | G18: =IF(B18=0,0,C18/B18) -> 0.38461538
A19: 46302 | B19: =COUNTIFS(Data!$D$2:$D$2284,"Omar.Mansour@vxi.com",Data!$B$2:$B$2284,A19) -> 14 | C19: =COUNTIFS(Data!$D$2:$D$2284,"Omar.Mansour@vxi.com",Data!$B$2:$B$2284,$A19,Data!$H$2:$H$2284,"Agent Opportunity") -> 5 | D19: =COUNTIFS(Data!$D$2:$D$2284,"Omar.Mansour@vxi.com",Data!$B$2:$B$2284,$A19,Data!$H$2:$H$2284,"Comcast Process/Tools") -> 6 | E19: =COUNTIFS(Data!$D$2:$D$2284,"Omar.Mansour@vxi.com",Data!$B$2:$B$2284,$A19,Data!$H$2:$H$2284,"Customer") -> 0 | F19: =COUNTIFS(Data!$D$2:$D$2284,"Omar.Mansour@vxi.com",Data!$B$2:$B$2284,$A19,Data!$H$2:$H$2284,"No Audio Found on I3") -> 3 | G19: =IF(B19=0,0,C19/B19) -> 0.35714286
A21: Audit Flags — row-level findings (QA review of Omar's 29 entries)
A22: Data ID | B22: Survey ID | C22: Severity | D22: Finding | E22: Recommended Action
A23: 2030 | B23: 11 | C23: High | D23: Test/junk entry: BPID = "11", Survey ID = "11". | E23: Delete from scrub file.
A24: 2215 | B24: 2196171839 | C24: High | D24: Same survey scrubbed twice with CONFLICTING RCA: Comcast Restriction (07-Oct) vs Agent Opp – Knowledge Gap. | E24: Keep one final RCA; remove the other.
A25: 2236 | B25: 2196171839 | C25: High | D25: Duplicate of above. Comment "Discovery / Identifying Customer Needs" fits "Did not ask discovery questions" better than Knowledge Gap. | E25: Merge with ID 2215; retag T2.
A26: 2277 | B26: 2197808496 | C26: Medium | D26: Survey submitted twice (IDs 2277 & 2278), both No Audio. | E26: Delete one row.
A27: 2120 | B27: 2195165826 | C27: Medium | D27: Tagged Comcast Outage, but comment says agent told customer "it's just you" without validating — misinformation is controllable. | E27: Re-review: likely Agent Opp – Incorrect/Incomplete Resolution.
A28: 2031 | B28: 30003055651790377517 | C28: Medium | D28: T2 = Communication/Soft Skills but comment itself concludes "Incorrect/Incomplete Resolution". Survey ID format (20 digits) unusual. | E28: Align T2 to comment; verify Survey ID.
A29: 2135 | B29: 2196814455 | C29: Low | D29: BPID typo "p-aelshe876" (missing "b") — breaks agent-level reporting. | E29: Correct to bp-aelshe876.
A30: 2275 | B30: 2197847600 | C30: Low | D30: Comment contains paste artifact "Pasted text". | E30: Clean comment.
A31: 2233 | B31: 2197495330 | C31: Low | D31: Comment is a tag list only, no call evidence. | E31: Add 1–2 lines of evidence.
A32: 2215 | B32: 2196171839 | C32: Low | D32: Handle time 3 seconds; ID 2273 left open 10+ hrs — timestamps not reliable for productivity. | E32: Submit form per call.
A34: Strengths
A35: ✔ Best-quality comments on the account: evidence-based, quotes the customer verbatim, explains WHY it is / is not controllable.
A36: ✔ Correctly separates "Another Agent's Opportunity" and "Positive feedback" from the handling agent — protects agents from unfair detractors.
A37: ✔ 100% Survey Date populated; all non-No-Audio rows have T2 + comment.
A39: Coaching Points for Omar
A40: 1. Accuracy over volume: 4 of 29 rows (14%) are junk/duplicate — check Survey ID before submitting.
A41: 2. Comcast tags at 34% vs 18% account: if the agent added misinformation or poor expectation-setting on top of an outage, tag Agent Opp.
A42: 3. Make T2 match the conclusion written in the comment.
A43: 4. Calibration session with a top-volume scrubber (e.g., Shereen Kamal) on 5 shared surveys.

Sheet Day over Day
A1: NPS Scrubbing — Day over Day (Account)
A2: Counts by scrub submission date · all formulas reference the Data tab
N4: Active Scrubbers: computed in Python (distinct count)
A5: Scrub Date | B5: Total Scrubs | C5: Agent Opp | D5: Customer | E5: Comcast | F5: No Audio | G5: VXI | H5: Agent Opp % | I5: Comcast % | J5: No Audio % | K5: DoD Δ Volume | L5: DoD Δ Agent Opp % (pts) | M5: Omar Scrubs | N5: Active Scrubbers
A6: 46302 | B6: =COUNTIFS(Data!$B$2:$B$2284,$A6) -> 110 | C6: =COUNTIFS(Data!$B$2:$B$2284,$A6,Data!$H$2:$H$2284,"Agent Opportunity") -> 71 | D6: =COUNTIFS(Data!$B$2:$B$2284,$A6,Data!$H$2:$H$2284,"Customer") -> 9 | E6: =COUNTIFS(Data!$B$2:$B$2284,$A6,Data!$H$2:$H$2284,"Comcast Process/Tools") -> 26 | F6: =COUNTIFS(Data!$B$2:$B$2284,$A6,Data!$H$2:$H$2284,"No Audio Found on I3") -> 3 | G6: =COUNTIFS(Data!$B$2:$B$2284,$A6,Data!$H$2:$H$2284,"VXI Process/Tools") -> 1 | H6: =IF(B6=0,0,C6/B6) -> 0.64545455 | I6: =IF(B6=0,0,E6/B6) -> 0.23636364 | J6: =IF(B6=0,0,F6/B6) -> 0.027272727 | K6: =B6-B7 -> 26 | L6: =(H6-H7)*100 -> 18.116883 | M6: =COUNTIFS(Data!$B$2:$B$2284,$A6,Data!$D$2:$D$2284,"Omar.Mansour@vxi.com") -> 14 | N6: 6
A7: 46301 | B7: =COUNTIFS(Data!$B$2:$B$2284,$A7) -> 84 | C7: =COUNTIFS(Data!$B$2:$B$2284,$A7,Data!$H$2:$H$2284,"Agent Opportunity") -> 39 | D7: =COUNTIFS(Data!$B$2:$B$2284,$A7,Data!$H$2:$H$2284,"Customer") -> 10 | E7: =COUNTIFS(Data!$B$2:$B$2284,$A7,Data!$H$2:$H$2284,"Comcast Process/Tools") -> 26 | F7: =COUNTIFS(Data!$B$2:$B$2284,$A7,Data!$H$2:$H$2284,"No Audio Found on I3") -> 9 | G7: =COUNTIFS(Data!$B$2:$B$2284,$A7,Data!$H$2:$H$2284,"VXI Process/Tools") -> 0 | H7: =IF(B7=0,0,C7/B7) -> 0.46428571 | I7: =IF(B7=0,0,E7/B7) -> 0.30952381 | J7: =IF(B7=0,0,F7/B7) -> 0.10714286 | K7: =B7-B8 -> 56 | L7: =(H7-H8)*100 -> -10.714286 | M7: =COUNTIFS(Data!$B$2:$B$2284,$A7,Data!$D$2:$D$2284,"Omar.Mansour@vxi.com") -> 13 | N7: 6
A8: 46299 | B8: =COUNTIFS(Data!$B$2:$B$2284,$A8) -> 28 | C8: =COUNTIFS(Data!$B$2:$B$2284,$A8,Data!$H$2:$H$2284,"Agent Opportunity") -> 16 | D8: =COUNTIFS(Data!$B$2:$B$2284,$A8,Data!$H$2:$H$2284,"Customer") -> 3 | E8: =COUNTIFS(Data!$B$2:$B$2284,$A8,Data!$H$2:$H$2284,"Comcast Process/Tools") -> 6 | F8: =COUNTIFS(Data!$B$2:$B$2284,$A8,Data!$H$2:$H$2284,"No Audio Found on I3") -> 2 | G8: =COUNTIFS(Data!$B$2:$B$2284,$A8,Data!$H$2:$H$2284,"VXI Process/Tools") -> 1 | H8: =IF(B8=0,0,C8/B8) -> 0.57142857 | I8: =IF(B8=0,0,E8/B8) -> 0.21428571 | J8: =IF(B8=0,0,F8/B8) -> 0.071428571 | K8: =B8-B9 -> 11 | L8: =(H8-H9)*100 -> 21.848739 | M8: =COUNTIFS(Data!$B$2:$B$2284,$A8,Data!$D$2:$D$2284,"Omar.Mansour@vxi.com") -> 0 | N8: 2
A9: 46298 | B9: =COUNTIFS(Data!$B$2:$B$2284,$A9) -> 17 | C9: =COUNTIFS(Data!$B$2:$B$2284,$A9,Data!$H$2:$H$2284,"Agent Opportunity") -> 6 | D9: =COUNTIFS(Data!$B$2:$B$2284,$A9,Data!$H$2:$H$2284,"Customer") -> 0 | E9: =COUNTIFS(Data!$B$2:$B$2284,$A9,Data!$H$2:$H$2284,"Comcast Process/Tools") -> 10 | F9: =COUNTIFS(Data!$B$2:$B$2284,$A9,Data!$H$2:$H$2284,"No Audio Found on I3") -> 1 | G9: =COUNTIFS(Data!$B$2:$B$2284,$A9,Data!$H$2:$H$2284,"VXI Process/Tools") -> 0 | H9: =IF(B9=0,0,C9/B9) -> 0.35294118 | I9: =IF(B9=0,0,E9/B9) -> 0.58823529 | J9: =IF(B9=0,0,F9/B9) -> 0.058823529 | K9: =B9-B10 -> 9 | L9: =(H9-H10)*100 -> -27.205882 | M9: =COUNTIFS(Data!$B$2:$B$2284,$A9,Data!$D$2:$D$2284,"Omar.Mansour@vxi.com") -> 0 | N9: 3
A10: 46297 | B10: =COUNTIFS(Data!$B$2:$B$2284,$A10) -> 8 | C10: =COUNTIFS(Data!$B$2:$B$2284,$A10,Data!$H$2:$H$2284,"Agent Opportunity") -> 5 | D10: =COUNTIFS(Data!$B$2:$B$2284,$A10,Data!$H$2:$H$2284,"Customer") -> 1 | E10: =COUNTIFS(Data!$B$2:$B$2284,$A10,Data!$H$2:$H$2284,"Comcast Process/Tools") -> 1 | F10: =COUNTIFS(Data!$B$2:$B$2284,$A10,Data!$H$2:$H$2284,"No Audio Found on I3") -> 1 | G10: =COUNTIFS(Data!$B$2:$B$2284,$A10,Data!$H$2:$H$2284,"VXI Process/Tools") -> 0 | H10: =IF(B10=0,0,C10/B10) -> 0.625 | I10: =IF(B10=0,0,E10/B10) -> 0.125 | J10: =IF(B10=0,0,F10/B10) -> 0.125 | K10: =B10-B11 -> 4 | L10: =(H10-H11)*100 -> -37.5 | M10: =COUNTIFS(Data!$B$2:$B$2284,$A10,Data!$D$2:$D$2284,"Omar.Mansour@vxi.com") -> 0 | N10: 2
A11: 46296 | B11: =COUNTIFS(Data!$B$2:$B$2284,$A11) -> 4 | C11: =COUNTIFS(Data!$B$2:$B$2284,$A11,Data!$H$2:$H$2284,"Agent Opportunity") -> 4 | D11: =COUNTIFS(Data!$B$2:$B$2284,$A11,Data!$H$2:$H$2284,"Customer") -> 0 | E11: =COUNTIFS(Data!$B$2:$B$2284,$A11,Data!$H$2:$H$2284,"Comcast Process/Tools") -> 0 | F11: =COUNTIFS(Data!$B$2:$B$2284,$A11,Data!$H$2:$H$2284,"No Audio Found on I3") -> 0 | G11: =COUNTIFS(Data!$B$2:$B$2284,$A11,Data!$H$2:$H$2284,"VXI Process/Tools") -> 0 | H11: =IF(B11=0,0,C11/B11) -> 1 | I11: =IF(B11=0,0,E11/B11) -> 0 | J11: =IF(B11=0,0,F11/B11) -> 0 | K11: =B11-B12 -> 0 | L11: =(H11-H12)*100 -> 25 | M11: =COUNTIFS(Data!$B$2:$B$2284,$A11,Data!$D$2:$D$2284,"Omar.Mansour@vxi.com") -> 0 | N11: 2
A12: 46294 | B12: =COUNTIFS(Data!$B$2:$B$2284,$A12) -> 4 | C12: =COUNTIFS(Data!$B$2:$B$2284,$A12,Data!$H$2:$H$2284,"Agent Opportunity") -> 3 | D12: =COUNTIFS(Data!$B$2:$B$2284,$A12,Data!$H$2:$H$2284,"Customer") -> 0 | E12: =COUNTIFS(Data!$B$2:$B$2284,$A12,Data!$H$2:$H$2284,"Comcast Process/Tools") -> 0 | F12: =COUNTIFS(Data!$B$2:$B$2284,$A12,Data!$H$2:$H$2284,"No Audio Found on I3") -> 1 | G12: =COUNTIFS(Data!$B$2:$B$2284,$A12,Data!$H$2:$H$2284,"VXI Process/Tools") -> 0 | H12: =IF(B12=0,0,C12/B12) -> 0.75 | I12: =IF(B12=0,0,E12/B12) -> 0 | J12: =IF(B12=0,0,F12/B12) -> 0.25 | K12: =B12-B13 -> -3 | L12: =(H12-H13)*100 -> -10.714286 | M12: =COUNTIFS(Data!$B$2:$B$2284,$A12,Data!$D$2:$D$2284,"Omar.Mansour@vxi.com") -> 2 | N12: 2
A13: 46293 | B13: =COUNTIFS(Data!$B$2:$B$2284,$A13) -> 7 | C13: =COUNTIFS(Data!$B$2:$B$2284,$A13,Data!$H$2:$H$2284,"Agent Opportunity") -> 6 | D13: =COUNTIFS(Data!$B$2:$B$2284,$A13,Data!$H$2:$H$2284,"Customer") -> 1 | E13: =COUNTIFS(Data!$B$2:$B$2284,$A13,Data!$H$2:$H$2284,"Comcast Process/Tools") -> 0 | F13: =COUNTIFS(Data!$B$2:$B$2284,$A13,Data!$H$2:$H$2284,"No Audio Found on I3") -> 0 | G13: =COUNTIFS(Data!$B$2:$B$2284,$A13,Data!$H$2:$H$2284,"VXI Process/Tools") -> 0 | H13: =IF(B13=0,0,C13/B13) -> 0.85714286 | I13: =IF(B13=0,0,E13/B13) -> 0 | J13: =IF(B13=0,0,F13/B13) -> 0 | K13: =B13-B14 -> 6 | L13: =(H13-H14)*100 -> -14.285714 | M13: =COUNTIFS(Data!$B$2:$B$2284,$A13,Data!$D$2:$D$2284,"Omar.Mansour@vxi.com") -> 0 | N13: 4
A14: 46292 | B14: =COUNTIFS(Data!$B$2:$B$2284,$A14) -> 1 | C14: =COUNTIFS(Data!$B$2:$B$2284,$A14,Data!$H$2:$H$2284,"Agent Opportunity") -> 1 | D14: =COUNTIFS(Data!$B$2:$B$2284,$A14,Data!$H$2:$H$2284,"Customer") -> 0 | E14: =COUNTIFS(Data!$B$2:$B$2284,$A14,Data!$H$2:$H$2284,"Comcast Process/Tools") -> 0 | F14: =COUNTIFS(Data!$B$2:$B$2284,$A14,Data!$H$2:$H$2284,"No Audio Found on I3") -> 0 | G14: =COUNTIFS(Data!$B$2:$B$2284,$A14,Data!$H$2:$H$2284,"VXI Process/Tools") -> 0 | H14: =IF(B14=0,0,C14/B14) -> 1 | I14: =IF(B14=0,0,E14/B14) -> 0 | J14: =IF(B14=0,0,F14/B14) -> 0 | K14: =B14-B15 -> -13 | L14: =(H14-H15)*100 -> 50 | M14: =COUNTIFS(Data!$B$2:$B$2284,$A14,Data!$D$2:$D$2284,"Omar.Mansour@vxi.com") -> 0 | N14: 1
A15: 46291 | B15: =COUNTIFS(Data!$B$2:$B$2284,$A15) -> 14 | C15: =COUNTIFS(Data!$B$2:$B$2284,$A15,Data!$H$2:$H$2284,"Agent Opportunity") -> 7 | D15: =COUNTIFS(Data!$B$2:$B$2284,$A15,Data!$H$2:$H$2284,"Customer") -> 4 | E15: =COUNTIFS(Data!$B$2:$B$2284,$A15,Data!$H$2:$H$2284,"Comcast Process/Tools") -> 2 | F15: =COUNTIFS(Data!$B$2:$B$2284,$A15,Data!$H$2:$H$2284,"No Audio Found on I3") -> 1 | G15: =COUNTIFS(Data!$B$2:$B$2284,$A15,Data!$H$2:$H$2284,"VXI Process/Tools") -> 0 | H15: =IF(B15=0,0,C15/B15) -> 0.5 | I15: =IF(B15=0,0,E15/B15) -> 0.14285714 | J15: =IF(B15=0,0,F15/B15) -> 0.071428571 | K15: =B15-B16 -> 5 | L15: =(H15-H16)*100 -> -38.888889 | M15: =COUNTIFS(Data!$B$2:$B$2284,$A15,Data!$D$2:$D$2284,"Omar.Mansour@vxi.com") -> 0 | N15: 3
A16: 46290 | B16: =COUNTIFS(Data!$B$2:$B$2284,$A16) -> 9 | C16: =COUNTIFS(Data!$B$2:$B$2284,$A16,Data!$H$2:$H$2284,"Agent Opportunity") -> 8 | D16: =COUNTIFS(Data!$B$2:$B$2284,$A16,Data!$H$2:$H$2284,"Customer") -> 1 | E16: =COUNTIFS(Data!$B$2:$B$2284,$A16,Data!$H$2:$H$2284,"Comcast Process/Tools") -> 0 | F16: =COUNTIFS(Data!$B$2:$B$2284,$A16,Data!$H$2:$H$2284,"No Audio Found on I3") -> 0 | G16: =COUNTIFS(Data!$B$2:$B$2284,$A16,Data!$H$2:$H$2284,"VXI Process/Tools") -> 0 | H16: =IF(B16=0,0,C16/B16) -> 0.88888889 | I16: =IF(B16=0,0,E16/B16) -> 0 | J16: =IF(B16=0,0,F16/B16) -> 0 | K16: =B16-B17 -> 7 | L16: =(H16-H17)*100 -> 38.888889 | M16: =COUNTIFS(Data!$B$2:$B$2284,$A16,Data!$D$2:$D$2284,"Omar.Mansour@vxi.com") -> 0 | N16: 4
A17: 46289 | B17: =COUNTIFS(Data!$B$2:$B$2284,$A17) -> 2 | C17: =COUNTIFS(Data!$B$2:$B$2284,$A17,Data!$H$2:$H$2284,"Agent Opportunity") -> 1 | D17: =COUNTIFS(Data!$B$2:$B$2284,$A17,Data!$H$2:$H$2284,"Customer") -> 0 | E17: =COUNTIFS(Data!$B$2:$B$2284,$A17,Data!$H$2:$H$2284,"Comcast Process/Tools") -> 1 | F17: =COUNTIFS(Data!$B$2:$B$2284,$A17,Data!$H$2:$H$2284,"No Audio Found on I3") -> 0 | G17: =COUNTIFS(Data!$B$2:$B$2284,$A17,Data!$H$2:$H$2284,"VXI Process/Tools") -> 0 | H17: =IF(B17=0,0,C17/B17) -> 0.5 | I17: =IF(B17=0,0,E17/B17) -> 0.5 | J17: =IF(B17=0,0,F17/B17) -> 0 | K17: =B17-B18 -> -15 | L17: =(H17-H18)*100 -> -8.8235294 | M17: =COUNTIFS(Data!$B$2:$B$2284,$A17,Data!$D$2:$D$2284,"Omar.Mansour@vxi.com") -> 0 | N17: 2
... A167: 46114 | B167: =COUNTIFS(Data!$B$2:$B$2284,$A167) -> 7 | C167: =COUNTIFS(Data!$B$2:$B$2284,$A167,Data!$H$2:$H$2284,"Agent Opportunity") -> 5 | D167: =COUNTIFS(Data!$B$2:$B$2284,$A167,Data!$H$2:$H$2284,"Customer") -> 1 | E167: =COUNTIFS(Data!$B$2:$B$2284,$A167,Data!$H$2:$H$2284,"Comcast Process/Tools") -> 0 | F167: =COUNTIFS(Data!$B$2:$B$2284,$A167,Data!$H$2:$H$2284,"No Audio Found on I3") -> 1 | G167: =COUNTIFS(Data!$B$2:$B$2284,$A167,Data!$H$2:$H$2284,"VXI Process/Tools") -> 0 | H167: =IF(B167=0,0,C167/B167) -> 0.71428571 | I167: =IF(B167=0,0,E167/B167) -> 0 | J167: =IF(B167=0,0,F167/B167) -> 0.14285714 | K167: =B167-B168 -> -2 | L167: =(H167-H168)*100 -> 4.7619048 | M167: =COUNTIFS(Data!$B$2:$B$2284,$A167,Data!$D$2:$D$2284,"Omar.Mansour@vxi.com") -> 0 | N167: 2
A168: 46113 | B168: =COUNTIFS(Data!$B$2:$B$2284,$A168) -> 9 | C168: =COUNTIFS(Data!$B$2:$B$2284,$A168,Data!$H$2:$H$2284,"Agent Opportunity") -> 6 | D168: =COUNTIFS(Data!$B$2:$B$2284,$A168,Data!$H$2:$H$2284,"Customer") -> 1 | E168: =COUNTIFS(Data!$B$2:$B$2284,$A168,Data!$H$2:$H$2284,"Comcast Process/Tools") -> 1 | F168: =COUNTIFS(Data!$B$2:$B$2284,$A168,Data!$H$2:$H$2284,"No Audio Found on I3") -> 1 | G168: =COUNTIFS(Data!$B$2:$B$2284,$A168,Data!$H$2:$H$2284,"VXI Process/Tools") -> 0 | H168: =IF(B168=0,0,C168/B168) -> 0.66666667 | I168: =IF(B168=0,0,E168/B168) -> 0.11111111 | J168: =IF(B168=0,0,F168/B168) -> 0.11111111 | K168: =0 -> 0 | L168: =0 -> 0 | M168: =COUNTIFS(Data!$B$2:$B$2284,$A168,Data!$D$2:$D$2284,"Omar.Mansour@vxi.com") -> 0 | N168: 2

Sheet Monthly Trend
A1: NPS Scrubbing — Month over Month
A2: Month = scrub submission month
A5: Month Start | B5: Month End | C5: Total | D5: Agent Opp | E5: Customer | F5: Comcast | G5: No Audio | H5: VXI | I5: Agent Opp % | J5: Comcast % | K5: MoM Δ Volume | L5: MoM Δ AO % (pts)
A6: 46113 | B6: 46142 | C6: =COUNTIFS(Data!$B$2:$B$2284,">="&A6,Data!$B$2:$B$2284,"<="&B6) -> 247 | D6: =COUNTIFS(Data!$B$2:$B$2284,">="&A6,Data!$B$2:$B$2284,"<="&B6,Data!$H$2:$H$2284,"Agent Opportunity") -> 147 | E6: =COUNTIFS(Data!$B$2:$B$2284,">="&A6,Data!$B$2:$B$2284,"<="&B6,Data!$H$2:$H$2284,"Customer") -> 25 | F6: =COUNTIFS(Data!$B$2:$B$2284,">="&A6,Data!$B$2:$B$2284,"<="&B6,Data!$H$2:$H$2284,"Comcast Process/Tools") -> 47 | G6: =COUNTIFS(Data!$B$2:$B$2284,">="&A6,Data!$B$2:$B$2284,"<="&B6,Data!$H$2:$H$2284,"No Audio Found on I3") -> 26 | H6: =COUNTIFS(Data!$B$2:$B$2284,">="&A6,Data!$B$2:$B$2284,"<="&B6,Data!$H$2:$H$2284,"VXI Process/Tools") -> 2 | I6: =IF(C6=0,0,D6/C6) -> 0.5951417 | J6: =IF(C6=0,0,F6/C6) -> 0.1902834 | K6: =0 -> 0 | L6: =0 -> 0
A7: 46143 | B7: 46173 | C7: =COUNTIFS(Data!$B$2:$B$2284,">="&A7,Data!$B$2:$B$2284,"<="&B7) -> 342 | D7: =COUNTIFS(Data!$B$2:$B$2284,">="&A7,Data!$B$2:$B$2284,"<="&B7,Data!$H$2:$H$2284,"Agent Opportunity") -> 220 | E7: =COUNTIFS(Data!$B$2:$B$2284,">="&A7,Data!$B$2:$B$2284,"<="&B7,Data!$H$2:$H$2284,"Customer") -> 33 | F7: =COUNTIFS(Data!$B$2:$B$2284,">="&A7,Data!$B$2:$B$2284,"<="&B7,Data!$H$2:$H$2284,"Comcast Process/Tools") -> 58 | G7: =COUNTIFS(Data!$B$2:$B$2284,">="&A7,Data!$B$2:$B$2284,"<="&B7,Data!$H$2:$H$2284,"No Audio Found on I3") -> 20 | H7: =COUNTIFS(Data!$B$2:$B$2284,">="&A7,Data!$B$2:$B$2284,"<="&B7,Data!$H$2:$H$2284,"VXI Process/Tools") -> 11 | I7: =IF(C7=0,0,D7/C7) -> 0.64327485 | J7: =IF(C7=0,0,F7/C7) -> 0.16959064 | K7: =C7-C6 -> 95 | L7: =(I7-I6)*100 -> 4.8133153
A8: 46174 | B8: 46203 | C8: =COUNTIFS(Data!$B$2:$B$2284,">="&A8,Data!$B$2:$B$2284,"<="&B8) -> 289 | D8: =COUNTIFS(Data!$B$2:$B$2284,">="&A8,Data!$B$2:$B$2284,"<="&B8,Data!$H$2:$H$2284,"Agent Opportunity") -> 178 | E8: =COUNTIFS(Data!$B$2:$B$2284,">="&A8,Data!$B$2:$B$2284,"<="&B8,Data!$H$2:$H$2284,"Customer") -> 23 | F8: =COUNTIFS(Data!$B$2:$B$2284,">="&A8,Data!$B$2:$B$2284,"<="&B8,Data!$H$2:$H$2284,"Comcast Process/Tools") -> 51 | G8: =COUNTIFS(Data!$B$2:$B$2284,">="&A8,Data!$B$2:$B$2284,"<="&B8,Data!$H$2:$H$2284,"No Audio Found on I3") -> 32 | H8: =COUNTIFS(Data!$B$2:$B$2284,">="&A8,Data!$B$2:$B$2284,"<="&B8,Data!$H$2:$H$2284,"VXI Process/Tools") -> 5 | I8: =IF(C8=0,0,D8/C8) -> 0.61591696 | J8: =IF(C8=0,0,F8/C8) -> 0.17647059 | K8: =C8-C7 -> -53 | L8: =(I8-I7)*100 -> -2.7357899
A9: 46204 | B9: 46234 | C9: =COUNTIFS(Data!$B$2:$B$2284,">="&A9,Data!$B$2:$B$2284,"<="&B9) -> 381 | D9: =COUNTIFS(Data!$B$2:$B$2284,">="&A9,Data!$B$2:$B$2284,"<="&B9,Data!$H$2:$H$2284,"Agent Opportunity") -> 259 | E9: =COUNTIFS(Data!$B$2:$B$2284,">="&A9,Data!$B$2:$B$2284,"<="&B9,Data!$H$2:$H$2284,"Customer") -> 27 | F9: =COUNTIFS(Data!$B$2:$B$2284,">="&A9,Data!$B$2:$B$2284,"<="&B9,Data!$H$2:$H$2284,"Comcast Process/Tools") -> 50 | G9: =COUNTIFS(Data!$B$2:$B$2284,">="&A9,Data!$B$2:$B$2284,"<="&B9,Data!$H$2:$H$2284,"No Audio Found on I3") -> 38 | H9: =COUNTIFS(Data!$B$2:$B$2284,">="&A9,Data!$B$2:$B$2284,"<="&B9,Data!$H$2:$H$2284,"VXI Process/Tools") -> 7 | I9: =IF(C9=0,0,D9/C9) -> 0.67979003 | J9: =IF(C9=0,0,F9/C9) -> 0.1312336 | K9: =C9-C8 -> 92 | L9: =(I9-I8)*100 -> 6.3873071
A10: 46235 | B10: 46265 | C10: =COUNTIFS(Data!$B$2:$B$2284,">="&A10,Data!$B$2:$B$2284,"<="&B10) -> 543 | D10: =COUNTIFS(Data!$B$2:$B$2284,">="&A10,Data!$B$2:$B$2284,"<="&B10,Data!$H$2:$H$2284,"Agent Opportunity") -> 357 | E10: =COUNTIFS(Data!$B$2:$B$2284,">="&A10,Data!$B$2:$B$2284,"<="&B10,Data!$H$2:$H$2284,"Customer") -> 46 | F10: =COUNTIFS(Data!$B$2:$B$2284,">="&A10,Data!$B$2:$B$2284,"<="&B10,Data!$H$2:$H$2284,"Comcast Process/Tools") -> 99 | G10: =COUNTIFS(Data!$B$2:$B$2284,">="&A10,Data!$B$2:$B$2284,"<="&B10,Data!$H$2:$H$2284,"No Audio Found on I3") -> 36 | H10: =COUNTIFS(Data!$B$2:$B$2284,">="&A10,Data!$B$2:$B$2284,"<="&B10,Data!$H$2:$H$2284,"VXI Process/Tools") -> 5 | I10: =IF(C10=0,0,D10/C10) -> 0.65745856 | J10: =IF(C10=0,0,F10/C10) -> 0.18232044 | K10: =C10-C9 -> 162 | L10: =(I10-I9)*100 -> -2.2331463
A11: 46266 | B11: 46295 | C11: =COUNTIFS(Data!$B$2:$B$2284,">="&A11,Data!$B$2:$B$2284,"<="&B11) -> 230 | D11: =COUNTIFS(Data!$B$2:$B$2284,">="&A11,Data!$B$2:$B$2284,"<="&B11,Data!$H$2:$H$2284,"Agent Opportunity") -> 156 | E11: =COUNTIFS(Data!$B$2:$B$2284,">="&A11,Data!$B$2:$B$2284,"<="&B11,Data!$H$2:$H$2284,"Customer") -> 27 | F11: =COUNTIFS(Data!$B$2:$B$2284,">="&A11,Data!$B$2:$B$2284,"<="&B11,Data!$H$2:$H$2284,"Comcast Process/Tools") -> 27 | G11: =COUNTIFS(Data!$B$2:$B$2284,">="&A11,Data!$B$2:$B$2284,"<="&B11,Data!$H$2:$H$2284,"No Audio Found on I3") -> 19 | H11: =COUNTIFS(Data!$B$2:$B$2284,">="&A11,Data!$B$2:$B$2284,"<="&B11,Data!$H$2:$H$2284,"VXI Process/Tools") -> 1 | I11: =IF(C11=0,0,D11/C11) -> 0.67826087 | J11: =IF(C11=0,0,F11/C11) -> 0.1173913 | K11: =C11-C10 -> -313 | L11: =(I11-I10)*100 -> 2.0802306
A12: 46296 | B12: 46326 | C12: =COUNTIFS(Data!$B$2:$B$2284,">="&A12,Data!$B$2:$B$2284,"<="&B12) -> 251 | D12: =COUNTIFS(Data!$B$2:$B$2284,">="&A12,Data!$B$2:$B$2284,"<="&B12,Data!$H$2:$H$2284,"Agent Opportunity") -> 141 | E12: =COUNTIFS(Data!$B$2:$B$2284,">="&A12,Data!$B$2:$B$2284,"<="&B12,Data!$H$2:$H$2284,"Customer") -> 23 | F12: =COUNTIFS(Data!$B$2:$B$2284,">="&A12,Data!$B$2:$B$2284,"<="&B12,Data!$H$2:$H$2284,"Comcast Process/Tools") -> 69 | G12: =COUNTIFS(Data!$B$2:$B$2284,">="&A12,Data!$B$2:$B$2284,"<="&B12,Data!$H$2:$H$2284,"No Audio Found on I3") -> 16 | H12: =COUNTIFS(Data!$B$2:$B$2284,">="&A12,Data!$B$2:$B$2284,"<="&B12,Data!$H$2:$H$2284,"VXI Process/Tools") -> 2 | I12: =IF(C12=0,0,D12/C12) -> 0.56175299 | J12: =IF(C12=0,0,F12/C12) -> 0.2749004 | K12: =C12-C11 -> 21 | L12: =(I12-I11)*100 -> -11.650788
A13: Total | C13: =SUM(C6:C12) -> 2283 | D13: =SUM(D6:D12) -> 1458 | E13: =SUM(E6:E12) -> 204 | F13: =SUM(F6:F12) -> 401 | G13: =SUM(G6:G12) -> 187 | H13: =SUM(H6:H12) -> 33 | I13: =D13/C13 -> 0.63863338 | J13: =F13/C13 -> 0.17564608
A14: October = MTD through 07-Oct-2026 (partial month).

Sheet Scrubber Scorecard
A1: Scrubber Scorecard & Calibration
A2: RCA mix per scrubber vs account — wide gaps signal calibration need
A5: Scrubber | B5: Email | C5: Total | D5: Agent Opp % | E5: Customer % | F5: Comcast % | G5: No Audio % | H5: T2 Filled % (excl. No Audio) | I5: Dup Survey IDs | J5: Bad BPID Format | K5: Median Min / Scrub | L5: AO % gap vs Account (pts) | M5: Calibration Flag
A6: Shereen Kamal | B6: shereen.kamal@vxi.com | C6: =COUNTIFS(Data!$D$2:$D$2284,B6) -> 382 | D6: =COUNTIFS(Data!$D$2:$D$2284,B6,Data!$H$2:$H$2284,"Agent Opportunity")/C6 -> 0.7617801 | E6: =COUNTIFS(Data!$D$2:$D$2284,B6,Data!$H$2:$H$2284,"Customer")/C6 -> 0.086387435 | F6: =COUNTIFS(Data!$D$2:$D$2284,B6,Data!$H$2:$H$2284,"Comcast Process/Tools")/C6 -> 0.10732984 | G6: =COUNTIFS(Data!$D$2:$D$2284,B6,Data!$H$2:$H$2284,"No Audio Found on I3")/C6 -> 0.031413613 | H6: =IFERROR(COUNTIFS(Data!$D$2:$D$2284,B6,Data!$H$2:$H$2284,"<>No Audio Found on I3",Data!$I$2:$I$2284,"<>")/COUNTIFS(Data!$D$2:$D$2284,B6,Data!$H$2:$H$2284,"<>No Audio Found on I3"),0) -> 1 | I6: =COUNTIFS(Data!$D$2:$D$2284,B6,Data!$L$2:$L$2284,"Y") -> 54 | J6: =COUNTIFS(Data!$D$2:$D$2284,B6,Data!$M$2:$M$2284,"N") -> 18 | K6: 2.4 | L6: =(D6-$D$18)*100 -> 12.314673 | M6: =IF(ABS(L6)>15,"Calibrate",IF(ABS(L6)>8,"Watch","Aligned")) -> Watch
A7: Mina Milad Khalaf Mansour | B7: mina.mansour@vxi.com | C7: =COUNTIFS(Data!$D$2:$D$2284,B7) -> 352 | D7: =COUNTIFS(Data!$D$2:$D$2284,B7,Data!$H$2:$H$2284,"Agent Opportunity")/C7 -> 0.65909091 | E7: =COUNTIFS(Data!$D$2:$D$2284,B7,Data!$H$2:$H$2284,"Customer")/C7 -> 0.11363636 | F7: =COUNTIFS(Data!$D$2:$D$2284,B7,Data!$H$2:$H$2284,"Comcast Process/Tools")/C7 -> 0.13920455 | G7: =COUNTIFS(Data!$D$2:$D$2284,B7,Data!$H$2:$H$2284,"No Audio Found on I3")/C7 -> 0.076704545 | H7: =IFERROR(COUNTIFS(Data!$D$2:$D$2284,B7,Data!$H$2:$H$2284,"<>No Audio Found on I3",Data!$I$2:$I$2284,"<>")/COUNTIFS(Data!$D$2:$D$2284,B7,Data!$H$2:$H$2284,"<>No Audio Found on I3"),0) -> 1 | I7: =COUNTIFS(Data!$D$2:$D$2284,B7,Data!$L$2:$L$2284,"Y") -> 28 | J7: =COUNTIFS(Data!$D$2:$D$2284,B7,Data!$M$2:$M$2284,"N") -> 0 | K7: 9.9 | L7: =(D7-$D$18)*100 -> 2.0457532 | M7: =IF(ABS(L7)>15,"Calibrate",IF(ABS(L7)>8,"Watch","Aligned")) -> Aligned
A8: Salma Ahmed | B8: salma.ahmed@vxi.com | C8: =COUNTIFS(Data!$D$2:$D$2284,B8) -> 316 | D8: =COUNTIFS(Data!$D$2:$D$2284,B8,Data!$H$2:$H$2284,"Agent Opportunity")/C8 -> 0.50949367 | E8: =COUNTIFS(Data!$D$2:$D$2284,B8,Data!$H$2:$H$2284,"Customer")/C8 -> 0.085443038 | F8: =COUNTIFS(Data!$D$2:$D$2284,B8,Data!$H$2:$H$2284,"Comcast Process/Tools")/C8 -> 0.24050633 | G8: =COUNTIFS(Data!$D$2:$D$2284,B8,Data!$H$2:$H$2284,"No Audio Found on I3")/C8 -> 0.14556962 | H8: =IFERROR(COUNTIFS(Data!$D$2:$D$2284,B8,Data!$H$2:$H$2284,"<>No Audio Found on I3",Data!$I$2:$I$2284,"<>")/COUNTIFS(Data!$D$2:$D$2284,B8,Data!$H$2:$H$2284,"<>No Audio Found on I3"),0) -> 1 | I8: =COUNTIFS(Data!$D$2:$D$2284,B8,Data!$L$2:$L$2284,"Y") -> 41 | J8: =COUNTIFS(Data!$D$2:$D$2284,B8,Data!$M$2:$M$2284,"N") -> 1 | K8: 4.9 | L8: =(D8-$D$18)*100 -> -12.913971 | M8: =IF(ABS(L8)>15,"Calibrate",IF(ABS(L8)>8,"Watch","Aligned")) -> Watch
A9: AbdelRahman Abdo | B9: Abdelrahman.Fouad@vxi.com | C9: =COUNTIFS(Data!$D$2:$D$2284,B9) -> 294 | D9: =COUNTIFS(Data!$D$2:$D$2284,B9,Data!$H$2:$H$2284,"Agent Opportunity")/C9 -> 0.64965986 | E9: =COUNTIFS(Data!$D$2:$D$2284,B9,Data!$H$2:$H$2284,"Customer")/C9 -> 0.047619048 | F9: =COUNTIFS(Data!$D$2:$D$2284,B9,Data!$H$2:$H$2284,"Comcast Process/Tools")/C9 -> 0.22789116 | G9: =COUNTIFS(Data!$D$2:$D$2284,B9,Data!$H$2:$H$2284,"No Audio Found on I3")/C9 -> 0.030612245 | H9: =IFERROR(COUNTIFS(Data!$D$2:$D$2284,B9,Data!$H$2:$H$2284,"<>No Audio Found on I3",Data!$I$2:$I$2284,"<>")/COUNTIFS(Data!$D$2:$D$2284,B9,Data!$H$2:$H$2284,"<>No Audio Found on I3"),0) -> 1 | I9: =COUNTIFS(Data!$D$2:$D$2284,B9,Data!$L$2:$L$2284,"Y") -> 4 | J9: =COUNTIFS(Data!$D$2:$D$2284,B9,Data!$M$2:$M$2284,"N") -> 6 | K9: 0.7 | L9: =(D9-$D$18)*100 -> 1.1026487 | M9: =IF(ABS(L9)>15,"Calibrate",IF(ABS(L9)>8,"Watch","Aligned")) -> Aligned
A10: Mohamed Ashour | B10: mohamed.ashour3@vxi.com | C10: =COUNTIFS(Data!$D$2:$D$2284,B10) -> 261 | D10: =COUNTIFS(Data!$D$2:$D$2284,B10,Data!$H$2:$H$2284,"Agent Opportunity")/C10 -> 0.67049808 | E10: =COUNTIFS(Data!$D$2:$D$2284,B10,Data!$H$2:$H$2284,"Customer")/C10 -> 0.088122605 | F10: =COUNTIFS(Data!$D$2:$D$2284,B10,Data!$H$2:$H$2284,"Comcast Process/Tools")/C10 -> 0.17241379 | G10: =COUNTIFS(Data!$D$2:$D$2284,B10,Data!$H$2:$H$2284,"No Audio Found on I3")/C10 -> 0.068965517 | H10: =IFERROR(COUNTIFS(Data!$D$2:$D$2284,B10,Data!$H$2:$H$2284,"<>No Audio Found on I3",Data!$I$2:$I$2284,"<>")/COUNTIFS(Data!$D$2:$D$2284,B10,Data!$H$2:$H$2284,"<>No Audio Found on I3"),0) -> 1 | I10: =COUNTIFS(Data!$D$2:$D$2284,B10,Data!$L$2:$L$2284,"Y") -> 47 | J10: =COUNTIFS(Data!$D$2:$D$2284,B10,Data!$M$2:$M$2284,"N") -> 0 | K10: 1.9 | L10: =(D10-$D$18)*100 -> 3.1864707 | M10: =IF(ABS(L10)>15,"Calibrate",IF(ABS(L10)>8,"Watch","Aligned")) -> Aligned
A11: Rahma El-Behery | B11: rahma.samir@vxi.com | C11: =COUNTIFS(Data!$D$2:$D$2284,B11) -> 259 | D11: =COUNTIFS(Data!$D$2:$D$2284,B11,Data!$H$2:$H$2284,"Agent Opportunity")/C11 -> 0.58687259 | E11: =COUNTIFS(Data!$D$2:$D$2284,B11,Data!$H$2:$H$2284,"Customer")/C11 -> 0.1042471 | F11: =COUNTIFS(Data!$D$2:$D$2284,B11,Data!$H$2:$H$2284,"Comcast Process/Tools")/C11 -> 0.18918919 | G11: =COUNTIFS(Data!$D$2:$D$2284,B11,Data!$H$2:$H$2284,"No Audio Found on I3")/C11 -> 0.1042471 | H11: =IFERROR(COUNTIFS(Data!$D$2:$D$2284,B11,Data!$H$2:$H$2284,"<>No Audio Found on I3",Data!$I$2:$I$2284,"<>")/COUNTIFS(Data!$D$2:$D$2284,B11,Data!$H$2:$H$2284,"<>No Audio Found on I3"),0) -> 1 | I11: =COUNTIFS(Data!$D$2:$D$2284,B11,Data!$L$2:$L$2284,"Y") -> 40 | J11: =COUNTIFS(Data!$D$2:$D$2284,B11,Data!$M$2:$M$2284,"N") -> 3 | K11: 1.8 | L11: =(D11-$D$18)*100 -> -5.176079 | M11: =IF(ABS(L11)>15,"Calibrate",IF(ABS(L11)>8,"Watch","Aligned")) -> Aligned
A12: Eslam Mohamed Farouk | B12: eslam.farouk@vxi.com | C12: =COUNTIFS(Data!$D$2:$D$2284,B12) -> 212 | D12: =COUNTIFS(Data!$D$2:$D$2284,B12,Data!$H$2:$H$2284,"Agent Opportunity")/C12 -> 0.77830189 | E12: =COUNTIFS(Data!$D$2:$D$2284,B12,Data!$H$2:$H$2284,"Customer")/C12 -> 0.08490566 | F12: =COUNTIFS(Data!$D$2:$D$2284,B12,Data!$H$2:$H$2284,"Comcast Process/Tools")/C12 -> 0.04245283 | G12: =COUNTIFS(Data!$D$2:$D$2284,B12,Data!$H$2:$H$2284,"No Audio Found on I3")/C12 -> 0.094339623 | H12: =IFERROR(COUNTIFS(Data!$D$2:$D$2284,B12,Data!$H$2:$H$2284,"<>No Audio Found on I3",Data!$I$2:$I$2284,"<>")/COUNTIFS(Data!$D$2:$D$2284,B12,Data!$H$2:$H$2284,"<>No Audio Found on I3"),0) -> 1 | I12: =COUNTIFS(Data!$D$2:$D$2284,B12,Data!$L$2:$L$2284,"Y") -> 10 | J12: =COUNTIFS(Data!$D$2:$D$2284,B12,Data!$M$2:$M$2284,"N") -> 2 | K12: 9.5 | L12: =(D12-$D$18)*100 -> 13.966851 | M12: =IF(ABS(L12)>15,"Calibrate",IF(ABS(L12)>8,"Watch","Aligned")) -> Watch
A13: Shrouk Ahmed | B13: Shrouk.Hanafy@vxi.com | C13: =COUNTIFS(Data!$D$2:$D$2284,B13) -> 79 | D13: =COUNTIFS(Data!$D$2:$D$2284,B13,Data!$H$2:$H$2284,"Agent Opportunity")/C13 -> 0.46835443 | E13: =COUNTIFS(Data!$D$2:$D$2284,B13,Data!$H$2:$H$2284,"Customer")/C13 -> 0.10126582 | F13: =COUNTIFS(Data!$D$2:$D$2284,B13,Data!$H$2:$H$2284,"Comcast Process/Tools")/C13 -> 0.25316456 | G13: =COUNTIFS(Data!$D$2:$D$2284,B13,Data!$H$2:$H$2284,"No Audio Found on I3")/C13 -> 0.16455696 | H13: =IFERROR(COUNTIFS(Data!$D$2:$D$2284,B13,Data!$H$2:$H$2284,"<>No Audio Found on I3",Data!$I$2:$I$2284,"<>")/COUNTIFS(Data!$D$2:$D$2284,B13,Data!$H$2:$H$2284,"<>No Audio Found on I3"),0) -> 1 | I13: =COUNTIFS(Data!$D$2:$D$2284,B13,Data!$L$2:$L$2284,"Y") -> 7 | J13: =COUNTIFS(Data!$D$2:$D$2284,B13,Data!$M$2:$M$2284,"N") -> 3 | K13: 10.6 | L13: =(D13-$D$18)*100 -> -17.027895 | M13: =IF(ABS(L13)>15,"Calibrate",IF(ABS(L13)>8,"Watch","Aligned")) -> Calibrate
A14: Anas Sayed abdelmaksod | B14: Anas.Sayedabdelmaksod@vxi.com | C14: =COUNTIFS(Data!$D$2:$D$2284,B14) -> 48 | D14: =COUNTIFS(Data!$D$2:$D$2284,B14,Data!$H$2:$H$2284,"Agent Opportunity")/C14 -> 0.20833333 | E14: =COUNTIFS(Data!$D$2:$D$2284,B14,Data!$H$2:$H$2284,"Customer")/C14 -> 0.10416667 | F14: =COUNTIFS(Data!$D$2:$D$2284,B14,Data!$H$2:$H$2284,"Comcast Process/Tools")/C14 -> 0.60416667 | G14: =COUNTIFS(Data!$D$2:$D$2284,B14,Data!$H$2:$H$2284,"No Audio Found on I3")/C14 -> 0.083333333 | H14: =IFERROR(COUNTIFS(Data!$D$2:$D$2284,B14,Data!$H$2:$H$2284,"<>No Audio Found on I3",Data!$I$2:$I$2284,"<>")/COUNTIFS(Data!$D$2:$D$2284,B14,Data!$H$2:$H$2284,"<>No Audio Found on I3"),0) -> 1 | I14: =COUNTIFS(Data!$D$2:$D$2284,B14,Data!$L$2:$L$2284,"Y") -> 10 | J14: =COUNTIFS(Data!$D$2:$D$2284,B14,Data!$M$2:$M$2284,"N") -> 1 | K14: 2.2 | L14: =(D14-$D$18)*100 -> -43.030004 | M14: =IF(ABS(L14)>15,"Calibrate",IF(ABS(L14)>8,"Watch","Aligned")) -> Calibrate
A15: Kareem Abosaif | B15: kareem.abosaif@vxi.com | C15: =COUNTIFS(Data!$D$2:$D$2284,B15) -> 30 | D15: =COUNTIFS(Data!$D$2:$D$2284,B15,Data!$H$2:$H$2284,"Agent Opportunity")/C15 -> 0.66666667 | E15: =COUNTIFS(Data!$D$2:$D$2284,B15,Data!$H$2:$H$2284,"Customer")/C15 -> 0.1 | F15: =COUNTIFS(Data!$D$2:$D$2284,B15,Data!$H$2:$H$2284,"Comcast Process/Tools")/C15 -> 0.066666667 | G15: =COUNTIFS(Data!$D$2:$D$2284,B15,Data!$H$2:$H$2284,"No Audio Found on I3")/C15 -> 0.16666667 | H15: =IFERROR(COUNTIFS(Data!$D$2:$D$2284,B15,Data!$H$2:$H$2284,"<>No Audio Found on I3",Data!$I$2:$I$2284,"<>")/COUNTIFS(Data!$D$2:$D$2284,B15,Data!$H$2:$H$2284,"<>No Audio Found on I3"),0) -> 1 | I15: =COUNTIFS(Data!$D$2:$D$2284,B15,Data!$L$2:$L$2284,"Y") -> 5 | J15: =COUNTIFS(Data!$D$2:$D$2284,B15,Data!$M$2:$M$2284,"N") -> 0 | K15: 5.1 | L15: =(D15-$D$18)*100 -> 2.803329 | M15: =IF(ABS(L15)>15,"Calibrate",IF(ABS(L15)>8,"Watch","Aligned")) -> Aligned
A16: Omar Mansour (Omar Ali Mohamed) | B16: Omar.Mansour@vxi.com | C16: =COUNTIFS(Data!$D$2:$D$2284,B16) -> 29 | D16: =COUNTIFS(Data!$D$2:$D$2284,B16,Data!$H$2:$H$2284,"Agent Opportunity")/C16 -> 0.37931034 | E16: =COUNTIFS(Data!$D$2:$D$2284,B16,Data!$H$2:$H$2284,"Customer")/C16 -> 0.13793103 | F16: =COUNTIFS(Data!$D$2:$D$2284,B16,Data!$H$2:$H$2284,"Comcast Process/Tools")/C16 -> 0.34482759 | G16: =COUNTIFS(Data!$D$2:$D$2284,B16,Data!$H$2:$H$2284,"No Audio Found on I3")/C16 -> 0.13793103 | H16: =IFERROR(COUNTIFS(Data!$D$2:$D$2284,B16,Data!$H$2:$H$2284,"<>No Audio Found on I3",Data!$I$2:$I$2284,"<>")/COUNTIFS(Data!$D$2:$D$2284,B16,Data!$H$2:$H$2284,"<>No Audio Found on I3"),0) -> 1 | I16: =COUNTIFS(Data!$D$2:$D$2284,B16,Data!$L$2:$L$2284,"Y") -> 4 | J16: =COUNTIFS(Data!$D$2:$D$2284,B16,Data!$M$2:$M$2284,"N") -> 2 | K16: 11.8 | L16: =(D16-$D$18)*100 -> -25.932303 | M16: =IF(ABS(L16)>15,"Calibrate",IF(ABS(L16)>8,"Watch","Aligned")) -> Calibrate
A17: Abdelrahman Mokhtar | B17: abdelrahman.mokhtar@vxi.com | C17: =COUNTIFS(Data!$D$2:$D$2284,B17) -> 21 | D17: =COUNTIFS(Data!$D$2:$D$2284,B17,Data!$H$2:$H$2284,"Agent Opportunity")/C17 -> 0.61904762 | E17: =COUNTIFS(Data!$D$2:$D$2284,B17,Data!$H$2:$H$2284,"Customer")/C17 -> 0.095238095 | F17: =COUNTIFS(Data!$D$2:$D$2284,B17,Data!$H$2:$H$2284,"Comcast Process/Tools")/C17 -> 0.19047619 | G17: =COUNTIFS(Data!$D$2:$D$2284,B17,Data!$H$2:$H$2284,"No Audio Found on I3")/C17 -> 0.095238095 | H17: =IFERROR(COUNTIFS(Data!$D$2:$D$2284,B17,Data!$H$2:$H$2284,"<>No Audio Found on I3",Data!$I$2:$I$2284,"<>")/COUNTIFS(Data!$D$2:$D$2284,B17,Data!$H$2:$H$2284,"<>No Audio Found on I3"),0) -> 1 | I17: =COUNTIFS(Data!$D$2:$D$2284,B17,Data!$L$2:$L$2284,"Y") -> 10 | J17: =COUNTIFS(Data!$D$2:$D$2284,B17,Data!$M$2:$M$2284,"N") -> 0 | K17: 85.2 | L17: =(D17-$D$18)*100 -> -1.9585758 | M17: =IF(ABS(L17)>15,"Calibrate",IF(ABS(L17)>8,"Watch","Aligned")) -> Aligned
A18: ACCOUNT | C18: =SUM(C6:C17) -> 2283 | D18: =COUNTIFS(Data!$H$2:$H$2284,"Agent Opportunity")/C18 -> 0.63863338 | E18: =COUNTIFS(Data!$H$2:$H$2284,"Customer")/C18 -> 0.08935611 | F18: =COUNTIFS(Data!$H$2:$H$2284,"Comcast Process/Tools")/C18 -> 0.17564608 | G18: =COUNTIFS(Data!$H$2:$H$2284,"No Audio Found on I3")/C18 -> 0.081909768 | H18: =COUNTIFS(Data!$H$2:$H$2284,"<>No Audio Found on I3",Data!$I$2:$I$2284,"<>")/COUNTIFS(Data!$H$2:$H$2284,"<>No Audio Found on I3") -> 1 | I18: =SUM(I6:I17) -> 260 | J18: =SUM(J6:J17) -> 36 | K18: 3.8
A19: Median Min/Scrub computed in Python (Completion−Start). Very low (<1 min) = possible bulk/form-prefill; very high = form left open. Flag thresholds: >15 pts Calibrate, >8 pts Watch (assumption).

Sheet RCA Drivers
A1: Detractor Drivers — Tier 1 & Tier 2
A2: What is driving detractors on the account, and where Omar differs
A5: Tier 1 RCA
A6: RCA | B6: Account # | C6: Account % | D6: Omar # | E6: Omar % | F6: Gap (pts) | H6: Account % denominator 2,283 = total rows (hardcoded from source)
A7: Agent Opportunity | B7: =COUNTIFS(Data!$H$2:$H$2284,A7) -> 1458 | C7: =B7/2283 -> 0.63863338 | D7: =COUNTIFS(Data!$H$2:$H$2284,A7,Data!$D$2:$D$2284,"Omar.Mansour@vxi.com") -> 11 | E7: =D7/COUNTIFS(Data!$D$2:$D$2284,"Omar.Mansour@vxi.com") -> 0.37931034 | F7: =(E7-C7)*100 -> -25.932303
A8: Customer | B8: =COUNTIFS(Data!$H$2:$H$2284,A8) -> 204 | C8: =B8/2283 -> 0.08935611 | D8: =COUNTIFS(Data!$H$2:$H$2284,A8,Data!$D$2:$D$2284,"Omar.Mansour@vxi.com") -> 4 | E8: =D8/COUNTIFS(Data!$D$2:$D$2284,"Omar.Mansour@vxi.com") -> 0.13793103 | F8: =(E8-C8)*100 -> 4.8574924
A9: Comcast Process/Tools | B9: =COUNTIFS(Data!$H$2:$H$2284,A9) -> 401 | C9: =B9/2283 -> 0.17564608 | D9: =COUNTIFS(Data!$H$2:$H$2284,A9,Data!$D$2:$D$2284,"Omar.Mansour@vxi.com") -> 10 | E9: =D9/COUNTIFS(Data!$D$2:$D$2284,"Omar.Mansour@vxi.com") -> 0.34482759 | F9: =(E9-C9)*100 -> 16.918151
A10: No Audio Found on I3 | B10: =COUNTIFS(Data!$H$2:$H$2284,A10) -> 187 | C10: =B10/2283 -> 0.081909768 | D10: =COUNTIFS(Data!$H$2:$H$2284,A10,Data!$D$2:$D$2284,"Omar.Mansour@vxi.com") -> 4 | E10: =D10/COUNTIFS(Data!$D$2:$D$2284,"Omar.Mansour@vxi.com") -> 0.13793103 | F10: =(E10-C10)*100 -> 5.6021267
A11: VXI Process/Tools | B11: =COUNTIFS(Data!$H$2:$H$2284,A11) -> 33 | C11: =B11/2283 -> 0.014454665 | D11: =COUNTIFS(Data!$H$2:$H$2284,A11,Data!$D$2:$D$2284,"Omar.Mansour@vxi.com") -> 0 | E11: =D11/COUNTIFS(Data!$D$2:$D$2284,"Omar.Mansour@vxi.com") -> 0 | F11: =(E11-C11)*100 -> -1.4454665
A14: Tier 2 — Agent Opportunity
A15: RCA T2 | B15: Account # | C15: % of Agent Opportunity | D15: Omar # | E15: Cumulative %
A16: Call Handling | B16: =COUNTIFS(Data!$H$2:$H$2284,"Agent Opportunity",Data!$I$2:$I$2284,A16) -> 596 | C16: =B16/COUNTIFS(Data!$H$2:$H$2284,"Agent Opportunity") -> 0.40877915 | D16: =COUNTIFS(Data!$H$2:$H$2284,"Agent Opportunity",Data!$I$2:$I$2284,A16,Data!$D$2:$D$2284,"Omar.Mansour@vxi.com") -> 0 | E16: =C16 -> 0.40877915
A17: Communication / Soft Skills | B17: =COUNTIFS(Data!$H$2:$H$2284,"Agent Opportunity",Data!$I$2:$I$2284,A17) -> 353 | C17: =B17/COUNTIFS(Data!$H$2:$H$2284,"Agent Opportunity") -> 0.24211248 | D17: =COUNTIFS(Data!$H$2:$H$2284,"Agent Opportunity",Data!$I$2:$I$2284,A17,Data!$D$2:$D$2284,"Omar.Mansour@vxi.com") -> 6 | E17: =E16+C17 -> 0.65089163
A18: Knowledge Gap | B18: =COUNTIFS(Data!$H$2:$H$2284,"Agent Opportunity",Data!$I$2:$I$2284,A18) -> 106 | C18: =B18/COUNTIFS(Data!$H$2:$H$2284,"Agent Opportunity") -> 0.072702332 | D18: =COUNTIFS(Data!$H$2:$H$2284,"Agent Opportunity",Data!$I$2:$I$2284,A18,Data!$D$2:$D$2284,"Omar.Mansour@vxi.com") -> 1 | E18: =E17+C18 -> 0.72359396
A19: Excessive Hold/Mute | B19: =COUNTIFS(Data!$H$2:$H$2284,"Agent Opportunity",Data!$I$2:$I$2284,A19) -> 99 | C19: =B19/COUNTIFS(Data!$H$2:$H$2284,"Agent Opportunity") -> 0.067901235 | D19: =COUNTIFS(Data!$H$2:$H$2284,"Agent Opportunity",Data!$I$2:$I$2284,A19,Data!$D$2:$D$2284,"Omar.Mansour@vxi.com") -> 2 | E19: =E18+C19 -> 0.7914952
A20: Incorrect/ Incomplete Resolution | B20: =COUNTIFS(Data!$H$2:$H$2284,"Agent Opportunity",Data!$I$2:$I$2284,A20) -> 92 | C20: =B20/COUNTIFS(Data!$H$2:$H$2284,"Agent Opportunity") -> 0.063100137 | D20: =COUNTIFS(Data!$H$2:$H$2284,"Agent Opportunity",Data!$I$2:$I$2284,A20,Data!$D$2:$D$2284,"Omar.Mansour@vxi.com") -> 1 | E20: =E19+C20 -> 0.85459534
A21: Ownership | B21: =COUNTIFS(Data!$H$2:$H$2284,"Agent Opportunity",Data!$I$2:$I$2284,A21) -> 72 | C21: =B21/COUNTIFS(Data!$H$2:$H$2284,"Agent Opportunity") -> 0.049382716 | D21: =COUNTIFS(Data!$H$2:$H$2284,"Agent Opportunity",Data!$I$2:$I$2284,A21,Data!$D$2:$D$2284,"Omar.Mansour@vxi.com") -> 1 | E21: =E20+C21 -> 0.90397805
A22: Tone - Pace | B22: =COUNTIFS(Data!$H$2:$H$2284,"Agent Opportunity",Data!$I$2:$I$2284,A22) -> 31 | C22: =B22/COUNTIFS(Data!$H$2:$H$2284,"Agent Opportunity") -> 0.021262003 | D22: =COUNTIFS(Data!$H$2:$H$2284,"Agent Opportunity",Data!$I$2:$I$2284,A22,Data!$D$2:$D$2284,"Omar.Mansour@vxi.com") -> 0 | E22: =E21+C22 -> 0.92524005
A23: Wrong ITG | B23: =COUNTIFS(Data!$H$2:$H$2284,"Agent Opportunity",Data!$I$2:$I$2284,A23) -> 28 | C23: =B23/COUNTIFS(Data!$H$2:$H$2284,"Agent Opportunity") -> 0.01920439 | D23: =COUNTIFS(Data!$H$2:$H$2284,"Agent Opportunity",Data!$I$2:$I$2284,A23,Data!$D$2:$D$2284,"Omar.Mansour@vxi.com") -> 0 | E23: =E22+C23 -> 0.94444444
A24: Incorrect/Incomplete ITG | B24: =COUNTIFS(Data!$H$2:$H$2284,"Agent Opportunity",Data!$I$2:$I$2284,A24) -> 28 | C24: =B24/COUNTIFS(Data!$H$2:$H$2284,"Agent Opportunity") -> 0.01920439 | D24: =COUNTIFS(Data!$H$2:$H$2284,"Agent Opportunity",Data!$I$2:$I$2284,A24,Data!$D$2:$D$2284,"Omar.Mansour@vxi.com") -> 0 | E24: =E23+C24 -> 0.96364883
A25: Customer Education - Setting Expectations | B25: =COUNTIFS(Data!$H$2:$H$2284,"Agent Opportunity",Data!$I$2:$I$2284,A25) -> 25 | C25: =B25/COUNTIFS(Data!$H$2:$H$2284,"Agent Opportunity") -> 0.017146776 | D25: =COUNTIFS(Data!$H$2:$H$2284,"Agent Opportunity",Data!$I$2:$I$2284,A25,Data!$D$2:$D$2284,"Omar.Mansour@vxi.com") -> 0 | E25: =E24+C25 -> 0.98079561
A26: Did not ask discovery questions | B26: =COUNTIFS(Data!$H$2:$H$2284,"Agent Opportunity",Data!$I$2:$I$2284,A26) -> 13 | C26: =B26/COUNTIFS(Data!$H$2:$H$2284,"Agent Opportunity") -> 0.0089163237 | D26: =COUNTIFS(Data!$H$2:$H$2284,"Agent Opportunity",Data!$I$2:$I$2284,A26,Data!$D$2:$D$2284,"Omar.Mansour@vxi.com") -> 0 | E26: =E25+C26 -> 0.98971193
A27: Missing ITG | B27: =COUNTIFS(Data!$H$2:$H$2284,"Agent Opportunity",Data!$I$2:$I$2284,A27) -> 8 | C27: =B27/COUNTIFS(Data!$H$2:$H$2284,"Agent Opportunity") -> 0.0054869684 | D27: =COUNTIFS(Data!$H$2:$H$2284,"Agent Opportunity",Data!$I$2:$I$2284,A27,Data!$D$2:$D$2284,"Omar.Mansour@vxi.com") -> 0 | E27: =E26+C27 -> 0.9951989
A28: Language Proficiency | B28: =COUNTIFS(Data!$H$2:$H$2284,"Agent Opportunity",Data!$I$2:$I$2284,A28) -> 5 | C28: =B28/COUNTIFS(Data!$H$2:$H$2284,"Agent Opportunity") -> 0.0034293553 | D28: =COUNTIFS(Data!$H$2:$H$2284,"Agent Opportunity",Data!$I$2:$I$2284,A28,Data!$D$2:$D$2284,"Omar.Mansour@vxi.com") -> 0 | E28: =E27+C28 -> 0.99862826
A29: Tools Navigation/Utilization | B29: =COUNTIFS(Data!$H$2:$H$2284,"Agent Opportunity",Data!$I$2:$I$2284,A29) -> 2 | C29: =B29/COUNTIFS(Data!$H$2:$H$2284,"Agent Opportunity") -> 0.0013717421 | D29: =COUNTIFS(Data!$H$2:$H$2284,"Agent Opportunity",Data!$I$2:$I$2284,A29,Data!$D$2:$D$2284,"Omar.Mansour@vxi.com") -> 0 | E29: =E28+C29 -> 1
A32: Tier 2 — Comcast Process/Tools
A33: RCA T2 | B33: Account # | C33: % of Comcast Process/Tools | D33: Omar # | E33: Cumulative %
A34: Dissatisfied with service | B34: =COUNTIFS(Data!$H$2:$H$2284,"Comcast Process/Tools",Data!$I$2:$I$2284,A34) -> 158 | C34: =B34/COUNTIFS(Data!$H$2:$H$2284,"Comcast Process/Tools") -> 0.39401496 | D34: =COUNTIFS(Data!$H$2:$H$2284,"Comcast Process/Tools",Data!$I$2:$I$2284,A34,Data!$D$2:$D$2284,"Omar.Mansour@vxi.com") -> 3 | E34: =C34 -> 0.39401496
A35: Complaints about the technician | B35: =COUNTIFS(Data!$H$2:$H$2284,"Comcast Process/Tools",Data!$I$2:$I$2284,A35) -> 112 | C35: =B35/COUNTIFS(Data!$H$2:$H$2284,"Comcast Process/Tools") -> 0.27930175 | D35: =COUNTIFS(Data!$H$2:$H$2284,"Comcast Process/Tools",Data!$I$2:$I$2284,A35,Data!$D$2:$D$2284,"Omar.Mansour@vxi.com") -> 1 | E35: =E34+C35 -> 0.67331671
A36: Outage | B36: =COUNTIFS(Data!$H$2:$H$2284,"Comcast Process/Tools",Data!$I$2:$I$2284,A36) -> 48 | C36: =B36/COUNTIFS(Data!$H$2:$H$2284,"Comcast Process/Tools") -> 0.11970075 | D36: =COUNTIFS(Data!$H$2:$H$2284,"Comcast Process/Tools",Data!$I$2:$I$2284,A36,Data!$D$2:$D$2284,"Omar.Mansour@vxi.com") -> 3 | E36: =E35+C36 -> 0.79301746
A37: IVR / Routing | B37: =COUNTIFS(Data!$H$2:$H$2284,"Comcast Process/Tools",Data!$I$2:$I$2284,A37) -> 26 | C37: =B37/COUNTIFS(Data!$H$2:$H$2284,"Comcast Process/Tools") -> 0.064837905 | D37: =COUNTIFS(Data!$H$2:$H$2284,"Comcast Process/Tools",Data!$I$2:$I$2284,A37,Data!$D$2:$D$2284,"Omar.Mansour@vxi.com") -> 0 | E37: =E36+C37 -> 0.85785536
A38: Comcast Restriction | B38: =COUNTIFS(Data!$H$2:$H$2284,"Comcast Process/Tools",Data!$I$2:$I$2284,A38) -> 23 | C38: =B38/COUNTIFS(Data!$H$2:$H$2284,"Comcast Process/Tools") -> 0.057356608 | D38: =COUNTIFS(Data!$H$2:$H$2284,"Comcast Process/Tools",Data!$I$2:$I$2284,A38,Data!$D$2:$D$2284,"Omar.Mansour@vxi.com") -> 0 | E38: =E37+C38 -> 0.91521197
A39: Comcast Restriction (add on the comment which Restriction) | B39: =COUNTIFS(Data!$H$2:$H$2284,"Comcast Process/Tools",Data!$I$2:$I$2284,A39) -> 21 | C39: =B39/COUNTIFS(Data!$H$2:$H$2284,"Comcast Process/Tools") -> 0.052369077 | D39: =COUNTIFS(Data!$H$2:$H$2284,"Comcast Process/Tools",Data!$I$2:$I$2284,A39,Data!$D$2:$D$2284,"Omar.Mansour@vxi.com") -> 3 | E39: =E38+C39 -> 0.96758105
A40: Comcast Tools Outage or update | B40: =COUNTIFS(Data!$H$2:$H$2284,"Comcast Process/Tools",Data!$I$2:$I$2284,A40) -> 13 | C40: =B40/COUNTIFS(Data!$H$2:$H$2284,"Comcast Process/Tools") -> 0.032418953 | D40: =COUNTIFS(Data!$H$2:$H$2284,"Comcast Process/Tools",Data!$I$2:$I$2284,A40,Data!$D$2:$D$2284,"Omar.Mansour@vxi.com") -> 0 | E40: =E39+C40 -> 1
A43: Tier 2 — Customer
A44: RCA T2 | B44: Account # | C44: % of Customer | D44: Omar # | E44: Cumulative %
A45: Another Agent's Opportunity | B45: =COUNTIFS(Data!$H$2:$H$2284,"Customer",Data!$I$2:$I$2284,A45) -> 103 | C45: =B45/COUNTIFS(Data!$H$2:$H$2284,"Customer") -> 0.50490196 | D45: =COUNTIFS(Data!$H$2:$H$2284,"Customer",Data!$I$2:$I$2284,A45,Data!$D$2:$D$2284,"Omar.Mansour@vxi.com") -> 2 | E45: =C45 -> 0.50490196
A46: Customer Provided the agent positive feedback | B46: =COUNTIFS(Data!$H$2:$H$2284,"Customer",Data!$I$2:$I$2284,A46) -> 74 | C46: =B46/COUNTIFS(Data!$H$2:$H$2284,"Customer") -> 0.3627451 | D46: =COUNTIFS(Data!$H$2:$H$2284,"Customer",Data!$I$2:$I$2284,A46,Data!$D$2:$D$2284,"Omar.Mansour@vxi.com") -> 2 | E46: =E45+C46 -> 0.86764706
A47: Customer Demanded for a US Rep | B47: =COUNTIFS(Data!$H$2:$H$2284,"Customer",Data!$I$2:$I$2284,A47) -> 15 | C47: =B47/COUNTIFS(Data!$H$2:$H$2284,"Customer") -> 0.073529412 | D47: =COUNTIFS(Data!$H$2:$H$2284,"Customer",Data!$I$2:$I$2284,A47,Data!$D$2:$D$2284,"Omar.Mansour@vxi.com") -> 0 | E47: =E46+C47 -> 0.94117647
A48: Customer Preferred to speak to the previous agent | B48: =COUNTIFS(Data!$H$2:$H$2284,"Customer",Data!$I$2:$I$2284,A48) -> 12 | C48: =B48/COUNTIFS(Data!$H$2:$H$2284,"Customer") -> 0.058823529 | D48: =COUNTIFS(Data!$H$2:$H$2284,"Customer",Data!$I$2:$I$2284,A48,Data!$D$2:$D$2284,"Omar.Mansour@vxi.com") -> 0 | E48: =E47+C48 -> 1
A51: Tier 2 — VXI Process/Tools
A52: RCA T2 | B52: Account # | C52: % of VXI Process/Tools | D52: Omar # | E52: Cumulative %
A53: Avaya issue | B53: =COUNTIFS(Data!$H$2:$H$2284,"VXI Process/Tools",Data!$I$2:$I$2284,A53) -> 11 | C53: =B53/COUNTIFS(Data!$H$2:$H$2284,"VXI Process/Tools") -> 0.33333333 | D53: =COUNTIFS(Data!$H$2:$H$2284,"VXI Process/Tools",Data!$I$2:$I$2284,A53,Data!$D$2:$D$2284,"Omar.Mansour@vxi.com") -> 0 | E53: =C53 -> 0.33333333
A54: ONE CTI down | B54: =COUNTIFS(Data!$H$2:$H$2284,"VXI Process/Tools",Data!$I$2:$I$2284,A54) -> 11 | C54: =B54/COUNTIFS(Data!$H$2:$H$2284,"VXI Process/Tools") -> 0.33333333 | D54: =COUNTIFS(Data!$H$2:$H$2284,"VXI Process/Tools",Data!$I$2:$I$2284,A54,Data!$D$2:$D$2284,"Omar.Mansour@vxi.com") -> 0 | E54: =E53+C54 -> 0.66666667
A55: Headset Issue | B55: =COUNTIFS(Data!$H$2:$H$2284,"VXI Process/Tools",Data!$I$2:$I$2284,A55) -> 6 | C55: =B55/COUNTIFS(Data!$H$2:$H$2284,"VXI Process/Tools") -> 0.18181818 | D55: =COUNTIFS(Data!$H$2:$H$2284,"VXI Process/Tools",Data!$I$2:$I$2284,A55,Data!$D$2:$D$2284,"Omar.Mansour@vxi.com") -> 0 | E55: =E54+C55 -> 0.84848485
A56: Global Protect / Connectivity | B56: =COUNTIFS(Data!$H$2:$H$2284,"VXI Process/Tools",Data!$I$2:$I$2284,A56) -> 5 | C56: =B56/COUNTIFS(Data!$H$2:$H$2284,"VXI Process/Tools") -> 0.15151515 | D56: =COUNTIFS(Data!$H$2:$H$2284,"VXI Process/Tools",Data!$I$2:$I$2284,A56,Data!$D$2:$D$2284,"Omar.Mansour@vxi.com") -> 0 | E56: =E55+C56 -> 1

Sheet Repeat Agents (BPID)
A1: Repeat Detractor Agents — Top 25 BPIDs by Agent Opportunity
A2: Coaching priority list for team leaders
A5: BPID | B5: Agent Opp # | C5: Total Scrubs | D5: Agent Opp % | E5: Top T2 Driver | F5: Top T2 # | G5: Last Scrub Date | H5: Last 30 Days AO #
A6: bp-hawad742 | B6: =COUNTIFS(Data!$E$2:$E$2284,A6,Data!$H$2:$H$2284,"Agent Opportunity") -> 47 | C6: =COUNTIFS(Data!$E$2:$E$2284,A6) -> 63 | D6: =B6/C6 -> 0.74603175 | E6: Call Handling | F6: =COUNTIFS(Data!$E$2:$E$2284,A6,Data!$H$2:$H$2284,"Agent Opportunity",Data!$I$2:$I$2284,E6) -> 30 | G6: 46301 | H6: =COUNTIFS(Data!$E$2:$E$2284,A6,Data!$H$2:$H$2284,"Agent Opportunity",Data!$B$2:$B$2284,">="&DATE(2026,9,7)) -> 2
A7: bp-gghane435 | B7: =COUNTIFS(Data!$E$2:$E$2284,A7,Data!$H$2:$H$2284,"Agent Opportunity") -> 42 | C7: =COUNTIFS(Data!$E$2:$E$2284,A7) -> 65 | D7: =B7/C7 -> 0.64615385 | E7: Call Handling | F7: =COUNTIFS(Data!$E$2:$E$2284,A7,Data!$H$2:$H$2284,"Agent Opportunity",Data!$I$2:$I$2284,E7) -> 21 | G7: 46301 | H7: =COUNTIFS(Data!$E$2:$E$2284,A7,Data!$H$2:$H$2284,"Agent Opportunity",Data!$B$2:$B$2284,">="&DATE(2026,9,7)) -> 4
A8: bp-watta702 | B8: =COUNTIFS(Data!$E$2:$E$2284,A8,Data!$H$2:$H$2284,"Agent Opportunity") -> 30 | C8: =COUNTIFS(Data!$E$2:$E$2284,A8) -> 35 | D8: =B8/C8 -> 0.85714286 | E8: Call Handling | F8: =COUNTIFS(Data!$E$2:$E$2284,A8,Data!$H$2:$H$2284,"Agent Opportunity",Data!$I$2:$I$2284,E8) -> 23 | G8: 46275 | H8: =COUNTIFS(Data!$E$2:$E$2284,A8,Data!$H$2:$H$2284,"Agent Opportunity",Data!$B$2:$B$2284,">="&DATE(2026,9,7)) -> 1
A9: bp-anail804 | B9: =COUNTIFS(Data!$E$2:$E$2284,A9,Data!$H$2:$H$2284,"Agent Opportunity") -> 30 | C9: =COUNTIFS(Data!$E$2:$E$2284,A9) -> 36 | D9: =B9/C9 -> 0.83333333 | E9: Communication / Soft Skills | F9: =COUNTIFS(Data!$E$2:$E$2284,A9,Data!$H$2:$H$2284,"Agent Opportunity",Data!$I$2:$I$2284,E9) -> 11 | G9: 46302 | H9: =COUNTIFS(Data!$E$2:$E$2284,A9,Data!$H$2:$H$2284,"Agent Opportunity",Data!$B$2:$B$2284,">="&DATE(2026,9,7)) -> 18
A10: bp-jhaana620 | B10: =COUNTIFS(Data!$E$2:$E$2284,A10,Data!$H$2:$H$2284,"Agent Opportunity") -> 29 | C10: =COUNTIFS(Data!$E$2:$E$2284,A10) -> 37 | D10: =B10/C10 -> 0.78378378 | E10: Call Handling | F10: =COUNTIFS(Data!$E$2:$E$2284,A10,Data!$H$2:$H$2284,"Agent Opportunity",Data!$I$2:$I$2284,E10) -> 13 | G10: 46302 | H10: =COUNTIFS(Data!$E$2:$E$2284,A10,Data!$H$2:$H$2284,"Agent Opportunity",Data!$B$2:$B$2284,">="&DATE(2026,9,7)) -> 4
A11: bp-amorsy796 | B11: =COUNTIFS(Data!$E$2:$E$2284,A11,Data!$H$2:$H$2284,"Agent Opportunity") -> 26 | C11: =COUNTIFS(Data!$E$2:$E$2284,A11) -> 43 | D11: =B11/C11 -> 0.60465116 | E11: Call Handling | F11: =COUNTIFS(Data!$E$2:$E$2284,A11,Data!$H$2:$H$2284,"Agent Opportunity",Data!$I$2:$I$2284,E11) -> 20 | G11: 46250 | H11: =COUNTIFS(Data!$E$2:$E$2284,A11,Data!$H$2:$H$2284,"Agent Opportunity",Data!$B$2:$B$2284,">="&DATE(2026,9,7)) -> 0
A12: bp-asakr617 | B12: =COUNTIFS(Data!$E$2:$E$2284,A12,Data!$H$2:$H$2284,"Agent Opportunity") -> 26 | C12: =COUNTIFS(Data!$E$2:$E$2284,A12) -> 31 | D12: =B12/C12 -> 0.83870968 | E12: Call Handling | F12: =COUNTIFS(Data!$E$2:$E$2284,A12,Data!$H$2:$H$2284,"Agent Opportunity",Data!$I$2:$I$2284,E12) -> 13 | G12: 46299 | H12: =COUNTIFS(Data!$E$2:$E$2284,A12,Data!$H$2:$H$2284,"Agent Opportunity",Data!$B$2:$B$2284,">="&DATE(2026,9,7)) -> 3
A13: bp-dmadbo843 | B13: =COUNTIFS(Data!$E$2:$E$2284,A13,Data!$H$2:$H$2284,"Agent Opportunity") -> 23 | C13: =COUNTIFS(Data!$E$2:$E$2284,A13) -> 27 | D13: =B13/C13 -> 0.85185185 | E13: Call Handling | F13: =COUNTIFS(Data!$E$2:$E$2284,A13,Data!$H$2:$H$2284,"Agent Opportunity",Data!$I$2:$I$2284,E13) -> 9 | G13: 46267 | H13: =COUNTIFS(Data!$E$2:$E$2284,A13,Data!$H$2:$H$2284,"Agent Opportunity",Data!$B$2:$B$2284,">="&DATE(2026,9,7)) -> 0
A14: bp-aetman106 | B14: =COUNTIFS(Data!$E$2:$E$2284,A14,Data!$H$2:$H$2284,"Agent Opportunity") -> 22 | C14: =COUNTIFS(Data!$E$2:$E$2284,A14) -> 41 | D14: =B14/C14 -> 0.53658537 | E14: Call Handling | F14: =COUNTIFS(Data!$E$2:$E$2284,A14,Data!$H$2:$H$2284,"Agent Opportunity",Data!$I$2:$I$2284,E14) -> 12 | G14: 46275 | H14: =COUNTIFS(Data!$E$2:$E$2284,A14,Data!$H$2:$H$2284,"Agent Opportunity",Data!$B$2:$B$2284,">="&DATE(2026,9,7)) -> 1
A15: bp-ygawda039 | B15: =COUNTIFS(Data!$E$2:$E$2284,A15,Data!$H$2:$H$2284,"Agent Opportunity") -> 21 | C15: =COUNTIFS(Data!$E$2:$E$2284,A15) -> 46 | D15: =B15/C15 -> 0.45652174 | E15: Call Handling | F15: =COUNTIFS(Data!$E$2:$E$2284,A15,Data!$H$2:$H$2284,"Agent Opportunity",Data!$I$2:$I$2284,E15) -> 11 | G15: 46275 | H15: =COUNTIFS(Data!$E$2:$E$2284,A15,Data!$H$2:$H$2284,"Agent Opportunity",Data!$B$2:$B$2284,">="&DATE(2026,9,7)) -> 1
A16: bp-onabwy363 | B16: =COUNTIFS(Data!$E$2:$E$2284,A16,Data!$H$2:$H$2284,"Agent Opportunity") -> 21 | C16: =COUNTIFS(Data!$E$2:$E$2284,A16) -> 27 | D16: =B16/C16 -> 0.77777778 | E16: Call Handling | F16: =COUNTIFS(Data!$E$2:$E$2284,A16,Data!$H$2:$H$2284,"Agent Opportunity",Data!$I$2:$I$2284,E16) -> 19 | G16: 46236 | H16: =COUNTIFS(Data!$E$2:$E$2284,A16,Data!$H$2:$H$2284,"Agent Opportunity",Data!$B$2:$B$2284,">="&DATE(2026,9,7)) -> 0
A17: bp-ehazem048 | B17: =COUNTIFS(Data!$E$2:$E$2284,A17,Data!$H$2:$H$2284,"Agent Opportunity") -> 20 | C17: =COUNTIFS(Data!$E$2:$E$2284,A17) -> 28 | D17: =B17/C17 -> 0.71428571 | E17: Call Handling | F17: =COUNTIFS(Data!$E$2:$E$2284,A17,Data!$H$2:$H$2284,"Agent Opportunity",Data!$I$2:$I$2284,E17) -> 6 | G17: 46258 | H17: =COUNTIFS(Data!$E$2:$E$2284,A17,Data!$H$2:$H$2284,"Agent Opportunity",Data!$B$2:$B$2284,">="&DATE(2026,9,7)) -> 0
... A30: bp-mhalee702 | B30: =COUNTIFS(Data!$E$2:$E$2284,A30,Data!$H$2:$H$2284,"Agent Opportunity") -> 16 | C30: =COUNTIFS(Data!$E$2:$E$2284,A30) -> 23 | D30: =B30/C30 -> 0.69565217 | E30: Call Handling | F30: =COUNTIFS(Data!$E$2:$E$2284,A30,Data!$H$2:$H$2284,"Agent Opportunity",Data!$I$2:$I$2284,E30) -> 10 | G30: 46302 | H30: =COUNTIFS(Data!$E$2:$E$2284,A30,Data!$H$2:$H$2284,"Agent Opportunity",Data!$B$2:$B$2284,">="&DATE(2026,9,7)) -> 1
A32: Top T2 Driver & Last Scrub Date computed in Python. Last 30 days = scrubs on/after 07-Sep-2026. Red = 3+ AO detractors in last 30 days → active coaching.

Sheet Data
A1: ID | B1: Scrub Date | C1: Scrubber | D1: Email | E1: BPID | F1: Survey ID | G1: Survey Date | H1: RCA (Clean) | I1: RCA T2 (Clean) | J1: Comment | K1: Handle Min | L1: Dup Survey ID | M1: BPID Format OK | N1: Original RCA | O1: Start time | P1: Completion time | R1: Notes
A2: 207 | B2: 46113 | C2: Shrouk Ahmed | D2: Shrouk.Hanafy@vxi.com | E2: bp-mashou692 | F2: 2133806148 | H2: Agent Opportunity | I2: Call Handling | J2: lack of empathy and very long mute | K2: 4.1 | L2: Y | M2: Y | N2: Agent Opportunity | O2: 46113.561 | P2: 46113.564 | R2: Source: NPS_Scrubbing1-2283.xlsx (uploaded by user), 2,283 rows.
A3: 208 | B3: 46113 | C3: Shrouk Ahmed | D3: Shrouk.Hanafy@vxi.com | E3: bp-mashou692 | F3: 2132948976 | H3: Comcast Process/Tools | I3: Dissatisfied with service | J3: customer dissatisfied with the bill | K3: 22.9 | L3: N | M3: Y | N3: Comcast Process or Tools | O3: 46113.564 | P3: 46113.58 | R3: Scrub Date = date of "Start time" (when the scrub was submitted).
A4: 209 | B4: 46113 | C4: Shrouk Ahmed | D4: Shrouk.Hanafy@vxi.com | E4: bp-mashou692 | F4: 2133427132 | H4: No Audio Found on I3 | K4: 11.2 | L4: N | M4: Y | N4: No Audio Found on I3 | O4: 46113.58 | P4: 46113.588 | R4: RCA (Clean) merges label variants: "Comcast Policy/Process or Tools"+"Comcast Process or Tools" -> Comcast Process/Tools; same for VXI.
A5: 210 | B5: 46113 | C5: Shrouk Ahmed | D5: Shrouk.Hanafy@vxi.com | E5: bp-mashou692 | F5: 2133806148 | H5: Agent Opportunity | I5: Call Handling | J5: long silence gap, lack of empathy | K5: 18.8 | L5: Y | M5: Y | N5: Agent Opportunity | O5: 46113.588 | P5: 46113.601 | R5: RCA T2 (Clean) = first filled T2 column (Agent/Customer/Comcast/VXI), label variants merged.
A6: 211 | B6: 46113 | C6: Shrouk Ahmed | D6: Shrouk.Hanafy@vxi.com | E6: bp-mashou692 | F6: 2133806148 | H6: Agent Opportunity | I6: Call Handling | J6: silence gap and lack of empathy | K6: 1 | L6: Y | M6: Y | N6: Agent Opportunity | O6: 46113.602 | P6: 46113.603 | R6: Handle Min = Completion time - Start time (minutes). Dup Survey ID / BPID Format computed in Python at build time.
A7: 212 | B7: 46113 | C7: Shrouk Ahmed | D7: Shrouk.Hanafy@vxi.com | E7: bp-mashou692 | F7: 2135586426 | H7: Customer | I7: Another Agent's Opportunity | J7: customer is satisfied from Ashour dissatisfied with the service and the previous agent, he didn't call after Ashour | K7: 5.9 | L7: N | M7: Y | N7: Customer | O7: 46113.603 | P7: 46113.607 | R7: Omar Mansour submits under display name "Omar Ali Mohamed" (Omar.Mansour@vxi.com).
A8: 213 | B8: 46113 | C8: Shereen Kamal | D8: shereen.kamal@vxi.com | E8: bp-hawad742 | F8: 10009054011774557093 | H8: Agent Opportunity | I8: Call Handling | J8: Point of Improv: -Tone of Voice (Not willing to help) -Monotonic -Active listening -Guessing instead of understand the issue -Attitude -Got the wrong case and arguing -talking with high pitch comes with attitude **Saying whisperly at 4:28 (How am I supposed to do this? ) - didn't own the issue **At 5:22 (I don't understand why i'm doing this?) which is not professional and reflect for the poor skills ** the cx asked for a manger at 6:40 followed by dead air from the agent till 6:52 Followed by Hold Without Permission ** 9 Hold without permission or refreshing (the agent refreshed the cx with dead air) **7 Silence Gap bettwen each hold instead of refreshing the cx - not using any soft skills to handel the customer even while offering an alternative | K8: 5.6 | L8: N | M8: Y | N8: Agent Opportunity | O8: 46113.905 | P8: 46113.909
A9: 215 | B9: 46113 | C9: Shereen Kamal | D9: shereen.kamal@vxi.com | E9: bp-hawad742 | F9: 10005025441774634266 | H9: Agent Opportunity | I9: Call Handling | J9: - the agent shoulden't confirm or disclose the full account number as the caller not account holder - the agent is driking somthing and the sound so obvious (3:09 ---3:25----3:29---3:40 ) - 5:29 the agent said ""So what would you like to do right now just to know"- "I just said that there is an amount needs to be paid so I'm not gonna be able to activate it " at 5:47 | K9: 3.2 | L9: N | M9: Y | N9: Agent Opportunity | O9: 46113.907 | P9: 46113.909
A10: 214 | B10: 46113 | C10: Shereen Kamal | D10: shereen.kamal@vxi.com | E10: bp-hawad742 | F10: 10007041571774637269 | H10: Agent Opportunity | I10: Communication / Soft Skills | J10: - the agent is not active which leads to misunderstanding and bad expriance to the cx - havey breath which looks as an attitude - the agent needs to let the cx confirm the info instead of saying it - obvious histation - the agent understood somthing else which lead to the customer furstration - A lot of silence Gap without hold and refreshing the hold with Silence Gap | K10: 2.7 | L10: N | M10: Y | N10: Agent Opportunity | O10: 46113.907 | P10: 46113.909
A11: 216 | B11: 46114 | C11: Shrouk Ahmed | D11: Shrouk.Hanafy@vxi.com | E11: bp-amorsy796 | F11: 2134496418 | H11: No Audio Found on I3 | K11: 2.3 | L11: N | M11: Y | N11: No Audio Found on I3 | O11: 46114.622 | P11: 46114.624
A12: 217 | B12: 46114 | C12: Shrouk Ahmed | D12: Shrouk.Hanafy@vxi.com | E12: bp-amorsy796 | F12: 2136093869 | H12: Customer | I12: Another Agent's Opportunity | J12: the other agent cancelled the service to make GSR, the agent Assem tried to get the service back but he faced an error on ASCR so he transferred the call to New sales department | K12: 8.6 | L12: N | M12: Y | N12: Customer | O12: 46114.624 | P12: 46114.63
A13: 218 | B13: 46114 | C13: Shrouk Ahmed | D13: Shrouk.Hanafy@vxi.com | E13: bp-gshohd151 | F13: 2134142395 | H13: Agent Opportunity | I13: Communication / Soft Skills | J13: very very long mute and tried to pitch at the begining of the call | K13: 20.8 | L13: N | M13: Y | N13: Agent Opportunity | O13: 46114.63 | P13: 46114.645
A14: 219 | B14: 46114 | C14: Shrouk Ahmed | D14: Shrouk.Hanafy@vxi.com | E14: bp-gshohd151 | F14: 2136003868 | H14: Agent Opportunity | I14: Communication / Soft Skills | J14: very long mute, we don't say the name of the account holder while we are verifying | K14: 22 | L14: N | M14: Y | N14: Agent Opportunity | O14: 46114.645 | P14: 46114.66
A15: 220 | B15: 46114 | C15: Shereen Kamal | D15: shereen.kamal@vxi.com | E15: bp-ysaeed642 | F15: 10006002121775133282 | H15: Agent Opportunity | I15: Communication / Soft Skills | J15: agent and SME handling skills | K15: 0.8 | L15: N | M15: Y | N15: Agent Opportunity | O15: 46114.873 | P15: 46114.874
A16: 221 | B16: 46114 | C16: Shereen Kamal | D16: shereen.kamal@vxi.com | E16: 100059960 | F16: 22005153331775063497 | H16: Agent Opportunity | I16: Knowledge Gap | J16: poor system navigation , mute and hold as well , confidence issues | K16: 4.5 | L16: N | M16: N | N16: Agent Opportunity | O16: 46114.881 | P16: 46114.884
A17: 222 | B17: 46114 | C17: Shereen Kamal | D17: shereen.kamal@vxi.com | E17: 100067085 | F17: 10003126061775065527 | H17: Agent Opportunity | I17: Call Handling | J17: mute and hold , some knowledge gaps due to the tenurity | K17: 3.2 | L17: N | M17: N | N17: Agent Opportunity | O17: 46114.885 | P17: 46114.887
A18: 223 | B18: 46118 | C18: Shereen Kamal | D18: shereen.kamal@vxi.com | E18: bp-ysaeed642 | F18: 13005009141775478483 | H18: Agent Opportunity | I18: Call Handling | J18: agent was more focused on the sale not on fixing the issue (login issue ) | K18: 0.9 | L18: N | M18: Y | N18: Agent Opportunity | O18: 46118.835 | P18: 46118.835
A19: 224 | B19: 46118 | C19: Shereen Kamal | D19: shereen.kamal@vxi.com | E19: bp-ysaeed642 | F19: 10004019911775232164 | H19: Agent Opportunity | I19: Call Handling | J19: setting expectation part on how to check his payment history on line | K19: 20.1 | L19: N | M19: Y | N19: Agent Opportunity | O19: 46118.835 | P19: 46118.849
A20: 225 | B20: 46118 | C20: Shereen Kamal | D20: shereen.kamal@vxi.com | E20: bp-hawad742 | F20: 10008019881775492372 | H20: Agent Opportunity | I20: Communication / Soft Skills | J20: agent has very weak handling skills , severe inturruptions | K20: 4.4 | L20: N | M20: Y | N20: Agent Opportunity | O20: 46118.849 | P20: 46118.852
A21: 226 | B21: 46118 | C21: Shereen Kamal | D21: shereen.kamal@vxi.com | E21: bp-yattal222 | F21: 10002038831775499233 | H21: Agent Opportunity | I21: Call Handling | J21: setting expectation part about the outage// isolation | K21: 15.1 | L21: N | M21: Y | N21: Agent Opportunity | O21: 46118.915 | P21: 46118.926
A22: 227 | B22: 46118 | C22: Shereen Kamal | D22: shereen.kamal@vxi.com | E22: bp-hawad742 | F22: 10011006371775481135 | H22: Agent Opportunity | I22: Communication / Soft Skills | J22: poor handling skills // mute and hold // setting expectation | K22: 3.2 | L22: N | M22: Y | N22: Agent Opportunity | O22: 46118.926 | P22: 46118.928
A23: 228 | B23: 46119 | C23: AbdelRahman Abdo | D23: Abdelrahman.Fouad@vxi.com | E23: bp-mnasse693 | F23: 2136693129 | H23: Agent Opportunity | I23: Wrong ITG | J23: need to start with the video ITG to handle the TV issue before the internet issue as it routed to TC | K23: 14.5 | L23: N | M23: Y | N23: Agent Opportunity | O23: 46119.566 | P23: 46119.576
A24: 229 | B24: 46119 | C24: AbdelRahman Abdo | D24: Abdelrahman.Fouad@vxi.com | E24: bp-sadel794 | F24: 2136718399 | H24: No Audio Found on I3 | K24: 0.8 | L24: N | M24: Y | N24: No Audio Found on I3 | O24: 46119.576 | P24: 46119.576
A25: 230 | B25: 46119 | C25: AbdelRahman Abdo | D25: Abdelrahman.Fouad@vxi.com | E25: bp-ehazem048 | F25: 2136794658 | H25: Agent Opportunity | I25: Knowledge Gap | J25: agent didn't inform the cst that we can send him the cell phone and we cannot check the mobile inventory of the store | K25: 9 | L25: N | M25: Y | N25: Agent Opportunity | O25: 46119.576 | P25: 46119.583
A26: 233 | B26: 46119 | C26: AbdelRahman Abdo | D26: Abdelrahman.Fouad@vxi.com | E26: bp-waboue567 | F26: 2133029909 | H26: Agent Opportunity | I26: Communication / Soft Skills | J26: agent could elaborate to the cst the reason for the steps and TC | K26: 160 | L26: N | M26: Y | N26: Agent Opportunity | O26: 46119.595 | P26: 46119.706
A27: 231 | B27: 46119 | C27: Shereen Kamal | D27: shereen.kamal@vxi.com | E27: bp-hawad742 | F27: 17006166081775506951 | H27: Agent Opportunity | I27: Communication / Soft Skills | J27: lack of understanding the issue , expressed frustration at the cx , lack of empathy , poor communication skills | K27: 1.5 | L27: N | M27: Y | N27: Agent Opportunity | O27: 46119.617 | P27: 46119.618
A28: 232 | B28: 46119 | C28: Shereen Kamal | D28: shereen.kamal@vxi.com | E28: bp-sshady806 | F28: 22003069031775508551 | H28: Agent Opportunity | I28: Communication / Soft Skills | J28: hold and mute , setting clear expectations in details as the cx is skeptical, so SHO would have saved us from that detractor on paramount | K28: 3.6 | L28: N | M28: Y | N28: Agent Opportunity | O28: 46119.652 | P28: 46119.654
A29: 235 | B29: 46119 | C29: AbdelRahman Abdo | D29: Abdelrahman.Fouad@vxi.com | E29: bp-waboue567 | F29: 2134134164 | H29: Agent Opportunity | I29: Knowledge Gap | J29: agent should confirm to the cst to make sure all subscription with the same email to enjoy the promo | K29: 43.8 | L29: N | M29: Y | N29: Agent Opportunity | O29: 46119.722 | P29: 46119.753
A30: 234 | B30: 46119 | C30: Shereen Kamal | D30: shereen.kamal@vxi.com | E30: bp-mmuham703 | F30: 10005002061775565138 | H30: Comcast Process/Tools | I30: Dissatisfied with service | J30: the cxc was false promised by the previous rep | K30: 0.7 | L30: N | M30: Y | N30: Comcast Process or Tools | O30: 46119.73 | P30: 46119.73
A31: 236 | B31: 46119 | C31: Shereen Kamal | D31: shereen.kamal@vxi.com | E31: bp-sshady806 | F31: 2137998837 | H31: Agent Opportunity | I31: Call Handling | J31: we should have educated the cx instead of the transfer about the reason why she has to pay the $25 to avoid the disconnection so the elaboration part wasn't enough | K31: 246.6 | L31: N | M31: Y | N31: Agent Opportunity | O31: 46119.744 | P31: 46119.915
A32: 237 | B32: 46119 | C32: Shereen Kamal | D32: shereen.kamal@vxi.com | E32: bp-sshady806 | F32: 2137915041 | H32: Agent Opportunity | I32: Call Handling | J32: call got escalated from the beginning of the call // no appropriate deescalation | K32: 1.9 | L32: N | M32: Y | N32: Agent Opportunity | O32: 46119.915 | P32: 46119.917
A33: 239 | B33: 46119 | C33: Mina Milad Khalaf Mansour | D33: mina.mansour@vxi.com | E33: bp-ghenry172 | F33: 10006010591775478835 | H33: Agent Opportunity | I33: Call Handling | J33: Dead Air / Excessive mutes / Not setting expectations regarding the credit that was put | K33: 47.3 | L33: N | M33: Y | N33: Agent Opportunity | O33: 46119.942 | P33: 46119.975
A34: 238 | B34: 46119 | C34: Eslam Mohamed Farouk | D34: eslam.farouk@vxi.com | E34: bp-mhassa707 | F34: 10006026361775492705 | H34: Agent Opportunity | I34: Call Handling | J34: CUSTOMER WAS VEEEEEEEERY FUNNY AND CHEERFUL, yet agent was so stale, tone of voice was flat, customer had a problem with her TV, agent started talking about lowering the bill, and steered the conversation to that | K34: 24 | L34: N | M34: Y | N34: Agent Opportunity | O34: 46119.944 | P34: 46119.961
A35: 240 | B35: 46119 | C35: Eslam Mohamed Farouk | D35: eslam.farouk@vxi.com | E35: bp-mmorsy511 | F35: 10004035001775502097 | H35: Agent Opportunity | I35: Call Handling | J35: agent was struggling to get the customer to pass auth, agent tone of voice is too bad to the point that customer got confused about what the agent was saying, agent remained silent on call trying to change customer's plan, call ended after agent silence for 8 Mins | K35: 24.2 | L35: N | M35: Y | N35: Agent Opportunity | O35: 46119.961 | P35: 46119.978
A36: 241 | B36: 46120 | C36: Mina Milad Khalaf Mansour | D36: mina.mansour@vxi.com | E36: bp-ghenry172 | F36: 10009012181775484142 | H36: Comcast Process/Tools | I36: Dissatisfied with service | J36: CX wasn't satisfied with our current prices and promotions, Even though the agent did his best and gave him a promotion. | K36: 19.7 | L36: N | M36: Y | N36: Comcast Process or Tools | O36: 46120.499 | P36: 46120.513
... A56: 261 | B56: 46121 | C56: Shereen Kamal | D56: shereen.kamal@vxi.com | E56: bp-hawad742 | F56: 2138480972 | H56: Agent Opportunity | I56: Communication / Soft Skills | J56: poor handling skills // frustrated intonation // lack of empathy, no sense of urgency | K56: 9.7 | L56: N | M56: Y | N56: Agent Opportunity | O56: 46121.648 | P56: 46121.655
A57: 262 | B57: 46121 | C57: Mina Milad Khalaf Mansour | D57: mina.mansour@vxi.com | E57: bp-aabdel744 | F57: 22004091221775566564 | H57: No Audio Found on I3 | K57: 0.1 | L57: N | M57: Y | N57: No Audio Found on I3 | O57: 46121.657 | P57: 46121.657
A58: 268 | B58: 46121 | C58: Mina Milad Khalaf Mansour | D58: mina.mansour@vxi.com | E58: bp-aabdel744 | F58: 10003021071775579082 | H58: Agent Opportunity | I58: Knowledge Gap | J58: Didn't quiet understand what the customer was trying to communicate at the middle of the call so the agent couldn't really pick up the clues the current issue that the customer had therefore couldn't try to resolve it , Didn't probe properly as well | K58: 1293.5 | L58: N | M58: Y | N58: Agent Opportunity | O58: 46121.657 | P58: 46122.556
A59: 263 | B59: 46121 | C59: Shereen Kamal | D59: shereen.kamal@vxi.com | E59: bp-jhaana620 | F59: 2138647688 | H59: Agent Opportunity | I59: Call Handling | J59: isolation // cx is dissatisfied about the previous rep | K59: 181.7 | L59: Y | M59: Y | N59: Agent Opportunity | O59: 46121.763 | P59: 46121.889
A60: 264 | B60: 46121 | C60: Shereen Kamal | D60: shereen.kamal@vxi.com | E60: bp-mmuham703 | F60: 2138647688 | H60: Comcast Process/Tools | I60: Comcast Restriction | J60: cx were dissatisfied about the other agent who took over the call after the transfer to disconnect | K60: 1.1 | L60: Y | M60: Y | N60: Comcast Process or Tools | O60: 46121.889 | P60: 46121.89
A61: 265 | B61: 46121 | C61: Eslam Mohamed Farouk | D61: eslam.farouk@vxi.com | E61: bp-welmag588 | F61: 2138110868 | H61: Agent Opportunity | I61: Call Handling | J61: Invalid transfer, customer's internet is down, agent refused to help customer since she didn't accept his sales offer | K61: 12.3 | L61: N | M61: Y | N61: Agent Opportunity | O61: 46121.977 | P61: 46121.986
A62: 266 | B62: 46121 | C62: Eslam Mohamed Farouk | D62: eslam.farouk@vxi.com | E62: bp-mabdel482 | F62: 2138454094 | H62: Agent Opportunity | I62: Call Handling | J62: agent mispelled customer's name, customer corrected that, agent mispelled customer's name again about 20 times during the call, 3AYL MOSTAFEEEEEZ | K62: 40.2 | L62: N | M62: Y | N62: Agent Opportunity | O62: 46121.986 | P62: 46122.014
A63: 267 | B63: 46122 | C63: Eslam Mohamed Farouk | D63: eslam.farouk@vxi.com | E63: bp-mabdel482 | F63: 2138448306 | H63: Agent Opportunity | I63: Call Handling | J63: possible call avoidance, 4min silence, customer dropped the call, agent called back | K63: 11.5 | L63: Y | M63: Y | N63: Agent Opportunity | O63: 46122.014 | P63: 46122.022
A64: 280 | B64: 46122 | C64: Eslam Mohamed Farouk | D64: eslam.farouk@vxi.com | E64: bp-welmag588 | F64: 2138697451 | H64: Customer | I64: Customer Provided the agent positive feedback | J64: customer wanted to know the address of the nearest store, agent provided the address customer ended the call hapily | K64: 1280.1 | L64: N | M64: Y | N64: Customer | O64: 46122.022 | P64: 46122.911
A65: 269 | B65: 46122 | C65: Mina Milad Khalaf Mansour | D65: mina.mansour@vxi.com | E65: bp-htaha363 | F65: 10008024241775581515 | H65: Comcast Process/Tools | I65: Comcast Tools Outage or update | J65: Agent tools outage / system issues and couldn't communicate and cx hanged up | K65: 12.9 | L65: N | M65: Y | N65: Comcast Process or Tools | O65: 46122.556 | P65: 46122.565
A66: 270 | B66: 46122 | C66: Mina Milad Khalaf Mansour | D66: mina.mansour@vxi.com | E66: bp-mhesha950 | F66: 13005002321775645321 | H66: Comcast Process/Tools | I66: Complaints about the technician | J66: CX had a multiple tech visits and wanted to get to a supervisor first thing in the call the agent tried to handle the call but her situation was urgent and wanted a tech today and a supervisor aswell. | K66: 78.8 | L66: N | M66: Y | N66: Comcast Process or Tools | O66: 46122.565 | P66: 46122.62
A67: 271 | B67: 46122 | C67: Shrouk Ahmed | D67: Shrouk.Hanafy@vxi.com | E67: bp-mahmed740 | F67: 2137911768 | H67: Agent Opportunity | I67: Communication / Soft Skills | J67: there was a very long mute and the customer kept saying Hello hello, the issue didn't get resolved and the customer called back twice | K67: 18.3 | L67: N | M67: Y | N67: Agent Opportunity | O67: 46122.668 | P67: 46122.681
A68: 273 | B68: 46122 | C68: Shrouk Ahmed | D68: Shrouk.Hanafy@vxi.com | E68: bp-gshohd151 | F68: 2138064115 | H68: Comcast Process/Tools | I68: Comcast Tools Outage or update | J68: Peacock issue as the Peacock account couldn't be activated many times | K68: 29.3 | L68: N | M68: Y | N68: Comcast Process or Tools | O68: 46122.681 | P68: 46122.701
A69: 272 | B69: 46122 | C69: Shereen Kamal | D69: shereen.kamal@vxi.com | E69: bp-mmuham703 | F69: 2136713238 | H69: Comcast Process/Tools | I69: Dissatisfied with service | J69: missed channels , no way to retrievbe them , agent did empathize , acknowlege the cx feelings , gave him credit and offered alternatives , cx is still not happy but no other option can be provided | K69: 2.4 | L69: N | M69: Y | N69: Comcast Process or Tools | O69: 46122.697 | P69: 46122.699
A70: 274 | B70: 46122 | C70: Shrouk Ahmed | D70: Shrouk.Hanafy@vxi.com | E70: bp-mehab439 | F70: 2138115463 | H70: No Audio Found on I3 | K70: 5.2 | L70: N | M70: Y | N70: No Audio Found on I3 | O70: 46122.701 | P70: 46122.705
A71: 275 | B71: 46122 | C71: Shrouk Ahmed | D71: Shrouk.Hanafy@vxi.com | E71: bp-mehab439 | F71: 2138263734 | H71: Comcast Process/Tools | I71: Dissatisfied with service | J71: customer is frustrated because of the channels that was removed from the plan, there is no hold, agent tried to explain and handle however his handling strategy was so weak and he attacked the company and this is very wrong | K71: 10.1 | L71: N | M71: Y | N71: Comcast Process or Tools | O71: 46122.705 | P71: 46122.712
A72: 276 | B72: 46122 | C72: Shrouk Ahmed | D72: Shrouk.Hanafy@vxi.com | E72: bp-gshohd151 | F72: 2138303201 | H72: Agent Opportunity | I72: Knowledge Gap | J72: she needs to open ITG slow connectivity to know the root cause analysis, the extender could be sent with a modem as a one package so you could say it as let me send you another modem with an extender to enhance your service. | K72: 10.6 | L72: N | M72: Y | N72: Agent Opportunity | O72: 46122.713 | P72: 46122.72
A73: 277 | B73: 46122 | C73: Shrouk Ahmed | D73: Shrouk.Hanafy@vxi.com | E73: bp-aamin484 | F73: 2138359373 | H73: Comcast Process/Tools | I73: Dissatisfied with service | J73: customer has an issue with his mobile he was very rude to the agent as he is from Egypt | K73: 44.7 | L73: N | M73: Y | N73: Comcast Process or Tools | O73: 46122.73 | P73: 46122.761
A74: 278 | B74: 46122 | C74: Shrouk Ahmed | D74: Shrouk.Hanafy@vxi.com | E74: bp-gshohd15 | F74: 2138700634 | H74: Comcast Process/Tools | I74: Dissatisfied with service | J74: agent sorted the issue and the customer showed appreciation to her however she was very frustrated from the service | K74: 9 | L74: N | M74: Y | N74: Comcast Process or Tools | O74: 46122.761 | P74: 46122.768
A75: 279 | B75: 46122 | C75: Shrouk Ahmed | D75: Shrouk.Hanafy@vxi.com | E75: bp-omahmo657 | F75: 2138737944 | H75: Agent Opportunity | I75: Communication / Soft Skills | J75: very unneeded silence gap which made the customer very frustrated and called us back | K75: 4.8 | L75: N | M75: Y | N75: Agent Opportunity | O75: 46122.768 | P75: 46122.771
A76: 281 | B76: 46122 | C76: Eslam Mohamed Farouk | D76: eslam.farouk@vxi.com | E76: bp-mhassa707 | F76: 2138476917 | H76: Agent Opportunity | I76: Call Handling | J76: customer had a problem with her mobile, agent did troubleshoot the issue, the reason of the detractor is the excessive hold | K76: 14.6 | L76: N | M76: Y | N76: Agent Opportunity | O76: 46122.911 | P76: 46122.921
A77: 282 | B77: 46123 | C77: Salma Ahmed | D77: salma.ahmed@vxi.com | E77: bp-mhalee702 | F77: 2136822004 | G77: 46115 | H77: Customer | I77: Another Agent's Opportunity | J77: Excessive mute , pitching before resolution | K77: 21.1 | L77: N | M77: Y | N77: Customer | O77: 46123.001 | P77: 46123.016
A78: 283 | B78: 46123 | C78: Salma Ahmed | D78: salma.ahmed@vxi.com | E78: bp-aetman106 | F78: 2138819846 | G78: 46121 | H78: Agent Opportunity | I78: Communication / Soft Skills | J78: worst time to put the cs on hold , hold policy , over authentication , acknowledgment and assurance , active listening and proper questioning | K78: 8 | L78: N | M78: Y | N78: Agent Opportunity | O78: 46123.016 | P78: 46123.022
A79: 284 | B79: 46123 | C79: Salma Ahmed | D79: salma.ahmed@vxi.com | E79: bp-maleel832 | F79: 2139052767 | G79: 46122 | H79: Comcast Process/Tools | I79: Complaints about the technician | J79: the long time of handling the call , cs was already frustrated, tech related , mute exceeding | K79: 8.9 | L79: Y | M79: Y | N79: Comcast Process or Tools | O79: 46123.023 | P79: 46123.029
A80: 285 | B80: 46123 | C80: Salma Ahmed | D80: salma.ahmed@vxi.com | E80: bp-ygawda039 | F80: 2139009839 | G80: 46122 | H80: Customer | I80: Another Agent's Opportunity | J80: cs got transferred to Samsung , non related comcast issue , mute exceeding though | K80: 4.3 | L80: N | M80: Y | N80: Customer | O80: 46123.032 | P80: 46123.035
A81: 286 | B81: 46125 | C81: AbdelRahman Abdo | D81: Abdelrahman.Fouad@vxi.com | E81: bp-sahmed797 | F81: 2138704464 | G81: 46121 | H81: Comcast Process/Tools | I81: Comcast Restriction | J81: cst was dissatisfied from the packaging prices | K81: 7.2 | L81: N | M81: Y | N81: Comcast Process or Tools | O81: 46125.76 | P81: 46125.765
A82: 287 | B82: 46125 | C82: AbdelRahman Abdo | D82: Abdelrahman.Fouad@vxi.com | E82: 2138705446 | F82: bp-waboue567 | G82: 46121 | H82: Agent Opportunity | I82: Communication / Soft Skills | J82: cst cannot handle the cst's frustration | K82: 0.7 | L82: N | M82: N | N82: Agent Opportunity | O82: 46125.766 | P82: 46125.766
A83: 288 | B83: 46125 | C83: AbdelRahman Abdo | D83: Abdelrahman.Fouad@vxi.com | E83: bp-waboue567 | F83: 2139231790 | G83: 46122 | H83: Agent Opportunity | I83: Communication / Soft Skills | J83: - | K83: 0.3 | L83: N | M83: Y | N83: Agent Opportunity | O83: 46125.766 | P83: 46125.766
A84: 289 | B84: 46125 | C84: AbdelRahman Abdo | D84: Abdelrahman.Fouad@vxi.com | E84: bp-mhafez261 | F84: 2139009243 | G84: 46122 | H84: Agent Opportunity | I84: Call Handling | J84: lack of empathy and tone of not willing to help the cst | K84: 3.3 | L84: N | M84: Y | N84: Agent Opportunity | O84: 46125.768 | P84: 46125.77
A85: 290 | B85: 46125 | C85: AbdelRahman Abdo | D85: Abdelrahman.Fouad@vxi.com | E85: bp-rhassa212 | F85: 2138615906 | G85: 46121 | H85: Comcast Process/Tools | I85: Dissatisfied with service | J85: cst is dissatisfied with the service and IVR long waiting time | K85: 9.6 | L85: N | M85: Y | N85: Comcast Process or Tools | O85: 46125.77 | P85: 46125.777
A86: 291 | B86: 46125 | C86: AbdelRahman Abdo | D86: Abdelrahman.Fouad@vxi.com | E86: bp-sahmed797 | F86: 2138995886 | G86: 46122 | H86: Agent Opportunity | I86: Wrong ITG | J86: - | K86: 3 | L86: N | M86: Y | N86: Agent Opportunity | O86: 46125.777 | P86: 46125.779
A87: 292 | B87: 46125 | C87: AbdelRahman Abdo | D87: Abdelrahman.Fouad@vxi.com | E87: bp-aaliaa108 | F87: 2138738331 | G87: 46121 | H87: No Audio Found on I3 | K87: 1.1 | L87: N | M87: Y | N87: No Audio Found on I3 | O87: 46125.779 | P87: 46125.78
A88: 293 | B88: 46125 | C88: AbdelRahman Abdo | D88: Abdelrahman.Fouad@vxi.com | E88: bp-aaliaa108 | F88: 2138826368 | G88: 46121 | H88: Customer | I88: Another Agent's Opportunity | J88: cst needed service outside of the support | K88: 6.2 | L88: N | M88: Y | N88: Customer | O88: 46125.78 | P88: 46125.784
A89: 294 | B89: 46125 | C89: Shrouk Ahmed | D89: Shrouk.Hanafy@vxi.com | E89: bp-mashou692 | F89: 2139031431 | G89: 46122 | H89: Agent Opportunity | I89: Call Handling | J89: long mute, no empathy | K89: 0.3 | L89: N | M89: Y | N89: Agent Opportunity | O89: 46125.851 | P89: 46125.851
A90: 295 | B90: 46125 | C90: Shrouk Ahmed | D90: Shrouk.Hanafy@vxi.com | E90: bp-omahmo657 | F90: 2139082770 | G90: 46122 | H90: Agent Opportunity | I90: Communication / Soft Skills | J90: over 30 mins mute!!!! agent got actioned | K90: 32.1 | L90: N | M90: Y | N90: Agent Opportunity | O90: 46125.851 | P90: 46125.873
A91: 296 | B91: 46125 | C91: Shrouk Ahmed | D91: Shrouk.Hanafy@vxi.com | E91: bp-omahmo657 | F91: 2139842591 | G91: 46125 | H91: Comcast Process/Tools | I91: Dissatisfied with service | J91: dissatisfied with the channels that were removed from comcast | K91: 3.9 | L91: N | M91: Y | N91: Comcast Process or Tools | O91: 46125.876 | P91: 46125.878
A92: 309 | B92: 46125 | C92: Shrouk Ahmed | D92: Shrouk.Hanafy@vxi.com | E92: by bp-yyehia213 | F92: 2139844659 | G92: 46125 | H92: Customer | I92: Another Agent's Opportunity | J92: previous agent downgraded the unlimited line for the customer without telling her anything | K92: 998.1 | L92: N | M92: N | N92: Customer | O92: 46125.879 | P92: 46126.572
A93: 297 | B93: 46125 | C93: Mina Milad Khalaf Mansour | D93: mina.mansour@vxi.com | E93: bp-oaboza433 | F93: 22005020231775822521 | G93: 46122 | H93: Agent Opportunity | I93: Wrong ITG | J93: CX had 2 concerns the agent addressed the first one and cx agreed to visit the store and for the second concern agent was lazy to even open an ITG for the second one and told him at the store they will be helping you for that one as well. | K93: 34.1 | L93: N | M93: Y | N93: Agent Opportunity | O93: 46125.931 | P93: 46125.955
A94: 299 | B94: 46125 | C94: Salma Ahmed | D94: salma.ahmed@vxi.com | E94: bp-maleel832 | F94: 2139930793 | G94: 46125 | H94: Agent Opportunity | I94: Call Handling | J94: The customer called because their service was shut off for non-payment, and one of their TVs was not working despite making a payment. After confirming the customer's identity and performing troubleshooting steps, the agent was able to restore the signal to the TV. The customer confirmed that the issue was resolved and expressed gratitude before ending the call. , mute exceeding , the agent missed to tell the SLA for the cs for the services to come back on , needed to set expactaions | K94: 29 | L94: Y | M94: Y | N94: Agent Opportunity | O94: 46125.947 | P94: 46125.967
A95: 298 | B95: 46125 | C95: Mina Milad Khalaf Mansour | D95: mina.mansour@vxi.com | E95: bp-gghane435 | F95: 2139024632 | G95: 46122 | H95: Comcast Process/Tools | I95: Outage | J95: CX wasn't happy about the ongoing channel outage situation. | K95: 6.2 | L95: N | M95: Y | N95: Comcast Process or Tools | O95: 46125.955 | P95: 46125.959
A96: 306 | B96: 46125 | C96: Mina Milad Khalaf Mansour | D96: mina.mansour@vxi.com | E96: bp-ghenry172 | F96: 2139050611 | G96: 46122 | H96: Comcast Process/Tools | I96: Complaints about the technician | J96: CX wasn't satisfied about the new placement of her internet modem that the last tech placed and couldn't connect to her remote work after then, Overall the CX was happy about the interaction but not with what happened previously with the tech and the agent did book her a tech to fix what happened. | K96: 45.4 | L96: N | M96: Y | N96: Comcast Process or Tools | O96: 46125.962 | P96: 46125.993
A97: 300 | B97: 46125 | C97: Salma Ahmed | D97: salma.ahmed@vxi.com | E97: bp-malsha213 | F97: 2139879392 | G97: 46125 | H97: VXI Process/Tools | I97: Avaya issue | J97: ghost call the call dropped , they called back but no respond , left a vm and on the sec time he already reached another agent | K97: 12 | L97: N | M97: Y | N97: VXI Process or Tools | O97: 46125.967 | P97: 46125.976
A98: 301 | B98: 46125 | C98: Eslam Mohamed Farouk | D98: eslam.farouk@vxi.com | E98: bp-lwael290 | F98: 2138876589 | G98: 46121 | H98: Agent Opportunity | I98: Call Handling | J98: customer called after being false promised of a battery and a free xfi pod, agent advised customer of the truth, no empathy or handling was done | K98: 2.7 | L98: N | M98: Y | N98: Agent Opportunity | O98: 46125.98 | P98: 46125.982
A99: 302 | B99: 46125 | C99: Eslam Mohamed Farouk | D99: eslam.farouk@vxi.com | E99: bp-mmorsy511 | F99: 2139006162 | G99: 46122 | H99: Agent Opportunity | I99: Call Handling | J99: customer had an outage, agent advised customer of that, no handling was done after that, didn't try to let customer know that we appreciate their patience while we upgrade our network, agent just told customer about the resolution and call ended there | K99: 4.6 | L99: N | M99: Y | N99: Agent Opportunity | O99: 46125.982 | P99: 46125.985
... A104: 307 | B104: 46125 | C104: Salma Ahmed | D104: salma.ahmed@vxi.com | E104: bp-helnab710 | F104: 2139050916 | G104: 46122 | H104: Customer | I104: Another Agent's Opportunity | J104: cs hang up the line before letting the agent verifiy the account , call lasted 51 sec , didn't respond when he called back | K104: 2.1 | L104: N | M104: Y | N104: Customer | O104: 46125.994 | P104: 46125.995
A105: 310 | B105: 46126 | C105: Shrouk Ahmed | D105: Shrouk.Hanafy@vxi.com | E105: bp-mehab439 | F105: 2140091831 | G105: 46125 | H105: No Audio Found on I3 | K105: 4.5 | L105: N | M105: Y | N105: No Audio Found on I3 | O105: 46126.572 | P105: 46126.575
A106: 324 | B106: 46126 | C106: AbdelRahman Abdo | D106: Abdelrahman.Fouad@vxi.com | E106: bp-amahmo172 | F106: 2139842605 | G106: 46125 | H106: Agent Opportunity | I106: Communication / Soft Skills | J106: agent didn't show empathy and has an issue in the active listening and didn't follow the LOQs | K106: 341.8 | L106: N | M106: Y | N106: Agent Opportunity | O106: 46126.579 | P106: 46126.817
A107: 311 | B107: 46126 | C107: Shrouk Ahmed | D107: Shrouk.Hanafy@vxi.com | E107: bp-omahmo657 | F107: 2140035505 | G107: 46125 | H107: Customer | I107: Customer Provided the agent positive feedback | J107: the customer asked the agent about the bill and she was satisfied with the agent and the new bill with the discount (passive) | K107: 5 | L107: N | M107: Y | N107: Customer | O107: 46126.598 | P107: 46126.602
A108: 312 | B108: 46126 | C108: Salma Ahmed | D108: salma.ahmed@vxi.com | E108: bp-maleel832 | F108: 2139052767 | G108: 46122 | H108: Agent Opportunity | I108: Knowledge Gap | J108: The customer contacted the agent regarding ongoing Internet issues, slow speeds and frequent drops over <DATE_TIME>. The agent performed troubleshooting steps, including checking the modem and running speed tests, which showed speeds lower than expected. After confirming the issues, the agent scheduled a technician appointment for <DATE_TIME> from <DATE_TIME> to further investigate the problem. The customer was also informed about potential upgrades to their service but declined any additional offers. The call concluded with the customer expressing satisfaction with the assistance provided. , call took too long to get a resloution , mute exceeding , pitching when the cs still | K108: 110.2 | L108: Y | M108: Y | N108: Agent Opportunity | O108: 46126.618 | P108: 46126.694
A109: 333 | B109: 46126 | C109: Mina Milad Khalaf Mansour | D109: mina.mansour@vxi.com | E109: bp-mhesha950 | F109: 2140194301 | G109: 46126 | H109: Comcast Process/Tools | I109: Dissatisfied with service | J109: Disconnected account that was overcharged future dated (Got charged for a payment on the 18th and the call was on the 14th), Agent tried to handle the customer but it made no sense for the customer and hanged up. | K109: 1343.1 | L109: N | M109: Y | N109: Comcast Process or Tools | O109: 46126.704 | P109: 46127.637
A110: 313 | B110: 46126 | C110: Shereen Kamal | D110: shereen.kamal@vxi.com | E110: bp-mmahdi703 | F110: 17004018601775222298 | H110: Comcast Process/Tools | I110: Dissatisfied with service | J110: missed channels , no way to retrievbe them , agent did empathize , acknowlege the cx feelings , gave him credit and offered alternatives , cx is still not happy but no other option can be provided | K110: 8.7 | L110: N | M110: Y | N110: Comcast Process or Tools | O110: 46126.722 | P110: 46126.728
A111: 314 | B111: 46126 | C111: Shereen Kamal | D111: shereen.kamal@vxi.com | E111: bp-jhaana620 | F111: 10004007801775827171 | H111: Agent Opportunity | I111: Call Handling | J111: hold and mute , delivery and clarity The customer called because their service was out, displaying a message that a channel would be available shortly. The agent confirmed there was an outage affecting the service and informed the customer that it would be resolved by approximately 12:20 PM Eastern time. The agent performed troubleshooting and reassured the customer throughout the call. The customer expressed understanding and appreciation for the assistance provided. | K111: 5.9 | L111: N | M111: Y | N111: Agent Opportunity | O111: 46126.728 | P111: 46126.732
A112: 316 | B112: 46126 | C112: Shereen Kamal | D112: shereen.kamal@vxi.com | E112: bp-jhaana620 | F112: 2139858452 | H112: Agent Opportunity | I112: Call Handling | J112: the supervisor did the wrong action , instead of offering to upgrade the plan to be eligible for the swap after 60 days as a work around the agent did say that there is no way to return the device back , yet the agent also got a knowledge gap in the same topic and he will be coached on it | K112: 22.9 | L112: N | M112: Y | N112: Agent Opportunity | O112: 46126.732 | P112: 46126.748
A113: 315 | B113: 46126 | C113: Salma Ahmed | D113: salma.ahmed@vxi.com | E113: bp-hsalem481 | F113: 2139029224 | G113: 46122 | H113: Comcast Process/Tools | I113: Comcast Restriction | J113: The customer, Lisa, called to activate service at her new apartment after moving from a larger home. She mentioned that the new apartment complex already has the modem installed and requested assistance in turning on the service. The agent was in the process of verifying the account and gathering necessary information, including the MAC address of the modem. The customer expressed some frustration during the call due to the complexities of the move and service transfer. cs was frustrated as she couldn't verify the account | K113: 11.4 | L113: N | M113: Y | N113: Comcast Process or Tools | O113: 46126.732 | P113: 46126.74
A114: 317 | B114: 46126 | C114: Salma Ahmed | D114: salma.ahmed@vxi.com | E114: bp-aomar509 | F114: 2139009214 | G114: 46122 | H114: Agent Opportunity | I114: Call Handling | J114: The customer called to inquire about the status of their 4K box, which they had not received despite being told it would be mailed. The agent confirmed that the box was not active on the account and raised a ticket to the shipping department to investigate the issue. The customer expressed frustration over previous incorrect box deliveries and charges. The agent assured the customer that they would follow up and confirmed the order for the correct box, offering express shipping at no charge. The agent also planned to check in with the customer the following Monday to ensure the issue was resolved. mute exceeding , lack of empathy , anagry customer call handelling | K114: 16.4 | L114: N | M114: Y | N114: Agent Opportunity | O114: 46126.74 | P114: 46126.752
A115: 319 | B115: 46126 | C115: Salma Ahmed | D115: salma.ahmed@vxi.com | E115: bp-helnab710 | F115: 2139009673 | G115: 46122 | H115: Customer | I115: Customer Preferred to speak to the previous agent | J115: cs wanted to speak a manager, excessive mute | K115: 34.2 | L115: N | M115: Y | N115: Customer | O115: 46126.753 | P115: 46126.777
A116: 318 | B116: 46126 | C116: Shrouk Ahmed | D116: Shrouk.Hanafy@vxi.com | E116: bp-mabdel894[ | F116: 2139854532 | G116: 46125 | H116: Agent Opportunity | I116: Call Handling | J116: agent promised to call back but he never did | K116: 2.9 | L116: N | M116: N | N116: Agent Opportunity | O116: 46126.763 | P116: 46126.765
A117: 320 | B117: 46126 | C117: Shereen Kamal | D117: shereen.kamal@vxi.com | E117: bp-hawad742 | F117: 2139845463 | H117: Agent Opportunity | I117: Call Handling | J117: lack of empathy, constant interruption for the cx , poor handling skills intolerable showing frustration at the cx | K117: 3.8 | L117: N | M117: Y | N117: Agent Opportunity | O117: 46126.779 | P117: 46126.782
A118: 321 | B118: 46126 | C118: Salma Ahmed | D118: salma.ahmed@vxi.com | E118: bp-helnab710 | F118: 2138992998 | G118: 46122 | H118: No Audio Found on I3 | K118: 0.8 | L118: N | M118: Y | N118: No Audio Found on I3 | O118: 46126.788 | P118: 46126.789
A119: 325 | B119: 46126 | C119: Salma Ahmed | D119: salma.ahmed@vxi.com | E119: bp-hsalem481 | F119: 2139901799 | G119: 46125 | H119: No Audio Found on I3 | K119: 42.1 | L119: N | M119: Y | N119: No Audio Found on I3 | O119: 46126.794 | P119: 46126.823
A120: 322 | B120: 46126 | C120: Shereen Kamal | D120: shereen.kamal@vxi.com | E120: bp-sshady806 | F120: 2139871805 | H120: Agent Opportunity | I120: Knowledge Gap | J120: the charges are valid , as much as we hate to admit but the charges arevalid giving the cx false hope that the charges will be waived and raising a ticket is no the correct course of action , we should have told her the truth completely and try to find an alternative to lower her bill | K120: 2.4 | L120: N | M120: Y | N120: Agent Opportunity | O120: 46126.794 | P120: 46126.795
A121: 323 | B121: 46126 | C121: Shereen Kamal | D121: shereen.kamal@vxi.com | E121: bp-sshady806 | F121: 10008011121776090025 | H121: Agent Opportunity | I121: Knowledge Gap | J121: 2139871805 .. shady the charges are valid , as much as we hate to admit but the charges arevalid giving the cx false hope that the charges will be waived and raising a ticket is no the correct course of action , we should have told her the truth completely and try to find an alternative to lower her bill | K121: 0.5 | L121: N | M121: Y | N121: Agent Opportunity | O121: 46126.799 | P121: 46126.8
A122: 326 | B122: 46126 | C122: AbdelRahman Abdo | D122: Abdelrahman.Fouad@vxi.com | E122: bp-mhafez261 | F122: 2139877260 | G122: 46125 | H122: Agent Opportunity | I122: Wrong ITG | J122: agent skipped the LOQs and didn't provide the accurate feedback, excessive hold | K122: 53.1 | L122: N | M122: Y | N122: Agent Opportunity | O122: 46126.817 | P122: 46126.853
A123: 327 | B123: 46126 | C123: AbdelRahman Abdo | D123: Abdelrahman.Fouad@vxi.com | E123: bp-sadel794 | F123: 2139875551 | G123: 46125 | H123: Agent Opportunity | I123: Knowledge Gap | J123: agent performed the required ITG and then proceeded with the correct ITG and routed him to tc due to wrong ITG | K123: 24.1 | L123: N | M123: Y | N123: Agent Opportunity | O123: 46126.865 | P123: 46126.881
...
